{
    "date": "2011-09-28",
    "items": [
        {
            "expanded_urls": "",
            "in_reply_to_status_id": "",
            "in_reply_to_user_id": "",
            "retweeted_status_id": "",
            "retweeted_status_timestamp": "",
            "retweeted_status_user_id": "",
            "source": "<a href=\"http://www.geocities.jp/twicli/\" rel=\"nofollow\">twicli</a>",
            "text": "\u6559\u6750\u3067\u65e5\u672c\u8a9e\u3092\u5b66\u3076\u5b66\u7fd2\u8005\u306f\u3001\u4f8b\u3048\u3070\"12.525\"\u306e\u767a\u97f3\u304c\u300c\u3058\u3085\u30460\u306b\u3044\u3066\u30931\u3054\u304a0\u306b\u30441\u30541\u300d\u3067\u3042\u308b\u3068\u3044\u3046\u3053\u3068\u3092\u3061\u3083\u3093\u3068\u5b66\u3079\u3066\u3044\u308b\u3093\u3060\u308d\u3046\u304b\u3001\u3068\u3044\u3046\u3053\u3068\u304c\u3075\u3068\u6c17\u306b\u306a\u3063\u305f",
            "timestamp": "2011-09-28 00:24:39 +0000",
            "tweet_id": "118843526757875713"
        },
        {
            "expanded_urls": "",
            "in_reply_to_status_id": "",
            "in_reply_to_user_id": "",
            "retweeted_status_id": "",
            "retweeted_status_timestamp": "",
            "retweeted_status_user_id": "",
            "source": "<a href=\"http://www.echofon.com/\" rel=\"nofollow\">Echofon</a>",
            "text": "\u4eca\u65e5\u306f\u8077\u5834\u306e\u98f2\u307f\u4f1a\u3060\u3063\u305f",
            "timestamp": "2011-09-28 13:56:19 +0000",
            "tweet_id": "119047788360253440"
        },
        {
            "expanded_urls": "",
            "in_reply_to_status_id": "",
            "in_reply_to_user_id": "",
            "retweeted_status_id": "",
            "retweeted_status_timestamp": "",
            "retweeted_status_user_id": "",
            "source": "<a href=\"http://www.echofon.com/\" rel=\"nofollow\">Echofon</a>",
            "text": "\u300c\u3053\u308c\u304b\u3089\u8ad6\u6587\u3092\u66f8\u304f\u82e5\u8005\u306e\u305f\u3081\u306b\u300d\u8aad\u4e86\u3002",
            "timestamp": "2011-09-28 14:49:25 +0000",
            "tweet_id": "119061151907717122"
        },
        {
            "expanded_urls": "",
            "in_reply_to_status_id": "",
            "in_reply_to_user_id": "",
            "retweeted_status_id": "119068011498967040",
            "retweeted_status_timestamp": "2011-09-28 15:16:40 +0000",
            "retweeted_status_user_id": "14218503",
            "source": "<a href=\"http://www.echofon.com/\" rel=\"nofollow\">Echofon</a>",
            "text": "RT @atomfe: \u4f55\u5ea6\u3082\u4f55\u5ea6\u3082\u7e70\u308a\u8fd4\u3057\u8a00\u3063\u3066\u307e\u3059\u304c\u3001\u30c9\u30a4\u30c4\u8a9e\u3092\u5b66\u3076\u306a\u3089\u30df\u30d2\u30e3\u30a8\u30eb\u30fb\u30a8\u30f3\u30c7\u306e\u300c\u30e2\u30e2\u300d\u3092\u8aad\u3080\u3053\u3068\u3092\u304a\u3059\u3059\u3081\u3057\u307e\u3059\u3002\u30a8\u30f3\u30c7\u306e\u4f5c\u54c1\u306f\u3069\u308c\u3082\u3059\u3070\u3089\u3057\u3044\u3093\u3060\u3051\u3069\u30e2\u30e2\u306f\u683c\u5225\u3002\u30c9\u30a4\u30c4\u8a9e\u306e\u8358\u53b3\u3055\u3068\u7ae5\u8a71\u3068\u3057\u3066\u306e\u7c21\u6613\u3055\u3092\u5408\u308f\u305b\u6301\u3064\u5091\u4f5c\u3002\u30e2\u30e2\u3092\u539f\u6587\u3067\u8aad\u3081\u305f\u3060\u3051\u3067\u30c9\u30a4\u30c4\u8a9e\u306e\u5b66 ...",
            "timestamp": "2011-09-28 23:29:24 +0000",
            "tweet_id": "119192010333761538"
        }
    ]
}