{
    "date": "2013-07-07",
    "items": [
        {
            "expanded_urls": "http://gohoo.org/alerts/130707/,http://gohoo.org/alerts/130707/",
            "in_reply_to_status_id": "",
            "in_reply_to_user_id": "",
            "retweeted_status_id": "353643573142503426",
            "retweeted_status_timestamp": "2013-07-06 22:36:12 +0000",
            "retweeted_status_user_id": "520117874",
            "source": "<a href=\"http://twitter.com/#!/download/ipad\" rel=\"nofollow\">Twitter for iPad</a>",
            "text": "RT @Watchdog_Japan: \u3010\u6ce8\u610f\u5831\u3011\u9ce9\u5c71\u6c0f\uff62\u76d7\u3093\u3060\u3082\u306e\u306f\u8fd4\u3059\u306e\u304c\u5f53\u7136\uff63 \u898b\u51fa\u3057\u8981\u6ce8\u610f\u3014\u7b2c1\u5831\u3015http://t.co/uQSArnA3IE\u3000\u2192\u9ce9\u5c71\u5143\u9996\u76f8\u304c\u4e2d\u56fd\u3067\u5c16\u95a3\u8af8\u5cf6\u306b\u3064\u3044\u3066\u300c\u76d7\u3093\u3060\u3082\u306e\u306f\u8fd4\u3059\u306e\u304c\u5f53\u7136\u300d\u3068\u767a\u8a00\u3057\u305f\u304b\u306e\u3088\u3046\u306b\u898b\u51fa\u3057\u3067\u5831\u9053\u3055\u308c\u305f\u304c\u3001\u5b9f\u969b\u306f\u8fd4\u9084\u3059\u3079\u304d\u3068\u2026",
            "timestamp": "2013-07-07 00:56:51 +0000",
            "tweet_id": "353678969213698048"
        },
        {
            "expanded_urls": "",
            "in_reply_to_status_id": "",
            "in_reply_to_user_id": "",
            "retweeted_status_id": "",
            "retweeted_status_timestamp": "",
            "retweeted_status_user_id": "",
            "source": "<a href=\"http://www.justsystems.com/jp/products/tweetatok/\" rel=\"nofollow\">Tweet ATOK</a>",
            "text": "\u521d\u3081\u3066\u5b50\u4f9b\u9023\u308c\u306e\u4e09\u4eba\u3067\u5916\u51fa\u3002",
            "timestamp": "2013-07-07 01:13:27 +0000",
            "tweet_id": "353683142919462912"
        },
        {
            "expanded_urls": "",
            "in_reply_to_status_id": "",
            "in_reply_to_user_id": "",
            "retweeted_status_id": "",
            "retweeted_status_timestamp": "",
            "retweeted_status_user_id": "",
            "source": "<a href=\"http://www.justsystems.com/jp/products/tweetatok/\" rel=\"nofollow\">Tweet ATOK</a>",
            "text": "\u5305\u4e01\u3068\u304b\u306e\u305f\u3068\u3048\u3067\u3042\u306e\u4eba\u3092\u64c1\u8b77\u3059\u308b\u610f\u898b\u304c\u6c17\u6301\u3061\u60aa\u304b\u3063\u305f",
            "timestamp": "2013-07-07 02:45:16 +0000",
            "tweet_id": "353706250963402752"
        },
        {
            "expanded_urls": "",
            "in_reply_to_status_id": "",
            "in_reply_to_user_id": "",
            "retweeted_status_id": "",
            "retweeted_status_timestamp": "",
            "retweeted_status_user_id": "",
            "source": "<a href=\"http://www.justsystems.com/jp/products/tweetatok/\" rel=\"nofollow\">Tweet ATOK</a>",
            "text": "\u4eba\u3092\u50b7\u3064\u3051\u308b\u306e\u306b\u7279\u5316\u3057\u305f\u5200\u304c\u624b\u306b\u5165\u3089\u306a\u304f\u306a\u3063\u3066\u5606\u3044\u3066\u3044\u308b\u72af\u7f6a\u8005\u96c6\u56e3\u306e\u3068\u3053\u308d\u306b\u73fe\u308c\u3066\u3001\u3082\u3063\u3068\u3044\u3044\u5200\u3092\u4f5c\u3063\u3066\u3084\u308b\u3068\u8a00\u3063\u3066\u305d\u306e\u901a\u308a\u306b\u4f5c\u3063\u305f\u5200\u5320\u3068\u540c\u3058\u3050\u3089\u3044\u60aa\u304f\u306a\u3044\u3068\u3044\u3046\u610f\u898b",
            "timestamp": "2013-07-07 02:48:35 +0000",
            "tweet_id": "353707086951096320"
        },
        {
            "expanded_urls": "",
            "in_reply_to_status_id": "353693891670704128",
            "in_reply_to_user_id": "50302462",
            "retweeted_status_id": "",
            "retweeted_status_timestamp": "",
            "retweeted_status_user_id": "",
            "source": "<a href=\"http://www.justsystems.com/jp/products/tweetatok/\" rel=\"nofollow\">Tweet ATOK</a>",
            "text": "@u_m4n1 \u3061\u3087\u3063\u3068\u6691\u3059\u304e\u308b\u304b\u3068\u601d\u3063\u305f\u3051\u3069\u3001\u6ce3\u3044\u305f\u308a\u3057\u306a\u304f\u3066\u5b89\u5fc3\u3057\u305f\u3002",
            "timestamp": "2013-07-07 03:00:01 +0000",
            "tweet_id": "353709963086012416"
        },
        {
            "expanded_urls": "",
            "in_reply_to_status_id": "",
            "in_reply_to_user_id": "",
            "retweeted_status_id": "",
            "retweeted_status_timestamp": "",
            "retweeted_status_user_id": "",
            "source": "<a href=\"http://www.justsystems.com/jp/products/tweetatok/\" rel=\"nofollow\">Tweet ATOK</a>",
            "text": "\u3044\u3061\u307e\u3055\u3093\u306e\u30c4\u30a4\u30fc\u30c8\u306b\u300c\u8fbf\u3005\u3057\u3044\u300d\u306a\u3093\u3066\u7528\u5b57\u304c\u3002\u308f\u3056\u308f\u3056\u4e00\u6587\u5b57\u305a\u3064\u5909\u63db\u3057\u305f\u306e\u304b\u3001\u5909\u306aIME\u306b\u3067\u3082\u5165\u3063\u3066\u3044\u308b\u306e\u304b\u3002",
            "timestamp": "2013-07-07 03:36:23 +0000",
            "tweet_id": "353719115011198980"
        },
        {
            "expanded_urls": "",
            "in_reply_to_status_id": "",
            "in_reply_to_user_id": "",
            "retweeted_status_id": "353723885369303040",
            "retweeted_status_timestamp": "2013-07-07 03:55:20 +0000",
            "retweeted_status_user_id": "5310852",
            "source": "<a href=\"http://www.justsystems.com/jp/products/tweetatok/\" rel=\"nofollow\">Tweet ATOK</a>",
            "text": "RT @tanakh: \u250c\u25cb\u2510\n\u2502\u5e78\u2502\n\u2502\u305b\u2502\n\u2502\u306b\u2502\n\u2502\u306a\u2502\n\u2502\u308c\u2502\n\u2502\u307e\u2502\n\u2502\u3059\u2502\n\u2502\u3088\u2502\n\u2502\u3046\u2502\n\u2502\u306b\u2502\n\u2514\u2500\u2518",
            "timestamp": "2013-07-07 04:03:03 +0000",
            "tweet_id": "353725825612390400"
        },
        {
            "expanded_urls": "",
            "in_reply_to_status_id": "",
            "in_reply_to_user_id": "",
            "retweeted_status_id": "",
            "retweeted_status_timestamp": "",
            "retweeted_status_user_id": "",
            "source": "<a href=\"http://sites.google.com/site/yorufukurou/\" rel=\"nofollow\">YoruFukurou</a>",
            "text": "JavaScript \u306a\u3069\u3067 C# \u306e decimal \u3092\u5b9f\u88c5\u3057\u3088\u3046\u3068\u3057\u305f\u3089\u76f8\u5f53\u3081\u3093\u3069\u3044\u306a\u2026\u3002",
            "timestamp": "2013-07-07 07:48:09 +0000",
            "tweet_id": "353782472628117505"
        },
        {
            "expanded_urls": "",
            "in_reply_to_status_id": "",
            "in_reply_to_user_id": "",
            "retweeted_status_id": "353735450164334592",
            "retweeted_status_timestamp": "2013-07-07 04:41:18 +0000",
            "retweeted_status_user_id": "19104463",
            "source": "<a href=\"http://www.justsystems.com/jp/products/tweetatok/\" rel=\"nofollow\">Tweet ATOK</a>",
            "text": "RT @cailia: \"\uac00\uc218 \ube44\uc5d0 \uac15\uac04 \ub2f9\ud588\ub2e4\" 50\ub300 \uc5ec\uc131 \uae30\uc18c...\uc9c0\ub09c 1\uc6d4 \ube44\ub85c\ubd80\ud130 \ud611\ubc15\u00b7\uac15\uac04 \ub4f1\uc744 \ub2f9\ud588\ub2e4\ub294 \ub0b4\uc6a9\uc744 \ub2f4\uc740 \ud50c\ub798\uce74\ub4dc\ub97c \ube44\uc758 \uccad\ub2f4\ub3d9 \uac74\ubb3c\uacfc \uc11c\uc6b8\uc911\uc559\uc9c0\uac80 \uccad\uc0ac \uc55e\uc5d0 \ubcf4\ub984\uc5ec \ub3d9\uc548 \uac78\uc5b4\ub1a8\ub2e4./ \u2026\uc544\uc90c\ub9c8...",
            "timestamp": "2013-07-07 10:03:21 +0000",
            "tweet_id": "353816497442914304"
        },
        {
            "expanded_urls": "",
            "in_reply_to_status_id": "",
            "in_reply_to_user_id": "",
            "retweeted_status_id": "",
            "retweeted_status_timestamp": "",
            "retweeted_status_user_id": "",
            "source": "<a href=\"http://twitter.com/download/iphone\" rel=\"nofollow\">Twitter for iPhone</a>",
            "text": "\"\uac00\uc218 \ube44\" \u3092 \"\uac00\uc2a4\ube44\" \u3068\u601d\u3044\u8fbc\u3093\u3067\uff1f\uff1f\uff1f\u3063\u3066\u306a\u3063\u305f",
            "timestamp": "2013-07-07 10:05:16 +0000",
            "tweet_id": "353816981826310144"
        },
        {
            "expanded_urls": "",
            "in_reply_to_status_id": "353822993249607681",
            "in_reply_to_user_id": "190470606",
            "retweeted_status_id": "",
            "retweeted_status_timestamp": "",
            "retweeted_status_user_id": "",
            "source": "<a href=\"http://www.justsystems.com/jp/products/tweetatok/\" rel=\"nofollow\">Tweet ATOK</a>",
            "text": "@pathos95606 \u6d3e\u751f\u8a9e\u306e\u4f5c\u308a\u65b9\u3068\u3057\u3066\u306f\u3001-ish \u3092\u3064\u3051\u3066 blackish \u3068\u306f\u8a00\u3048\u307e\u3059\u306d\u3002\u3082\u3061\u308d\u3093\u30d6\u30e9\u30c3\u30af\u4f01\u696d\u7684\u306a\u3068\u3044\u3046\u610f\u5473\u3067\u306f\u306a\u3044\u3067\u3059\u304c\u3002",
            "timestamp": "2013-07-07 10:45:25 +0000",
            "tweet_id": "353827083367088128"
        },
        {
            "expanded_urls": "",
            "in_reply_to_status_id": "",
            "in_reply_to_user_id": "",
            "retweeted_status_id": "",
            "retweeted_status_timestamp": "",
            "retweeted_status_user_id": "",
            "source": "<a href=\"http://www.justsystems.com/jp/products/tweetatok/\" rel=\"nofollow\">Tweet ATOK</a>",
            "text": "\u300c\u7a7a\u3082\u98db\u3079\u308b\u306f\u305a\u300d\u306f\u300c\u3060\u3063\u3066\u300d\u300c\u3055\u3048\u300d\u300c\u307e\u3067\u300d\u3068\u304b\u3082\u3044\u3051\u308b\u3093\u3058\u3083\u306a\u3044\u304b\u306a\u3002",
            "timestamp": "2013-07-07 10:46:41 +0000",
            "tweet_id": "353827403237310464"
        },
        {
            "expanded_urls": "",
            "in_reply_to_status_id": "",
            "in_reply_to_user_id": "",
            "retweeted_status_id": "",
            "retweeted_status_timestamp": "",
            "retweeted_status_user_id": "",
            "source": "<a href=\"http://www.justsystems.com/jp/products/tweetatok/\" rel=\"nofollow\">Tweet ATOK</a>",
            "text": "\u59bb\u304c\u5b50\u4f9b\uff08\uff11\u304b\u6708\uff09\u306b\u98f2\u307e\u305b\u3088\u3046\u3068\u30cf\u30c1\u30df\u30c4\u3092\u8cb7\u3063\u3066\u304d\u305f\u3002\u8d64\u3061\u3083\u3093\u306b\u30cf\u30c1\u30df\u30c4\u306f\u30c0\u30e1\u3060\u3068\u3044\u3046\u306e\u306f\u65e5\u672c\u4eba\u306e\u5e38\u8b58\u3060\u3068\u601d\u3046\u3093\u3060\u3051\u3069\u3001\u305d\u3046\u3044\u3048\u3070\u3069\u3046\u3044\u3046\u7d4c\u8def\u3067\u77e5\u3063\u305f\u3093\u3060\u3063\u3051\u3002\u59bb\u304c\u77e5\u3089\u306a\u304b\u3063\u305f\u306e\u306f\u4e2d\u56fd\u4eba\u3060\u304b\u3089\u3060\u308d\u3046\u304b\u3002",
            "timestamp": "2013-07-07 10:56:29 +0000",
            "tweet_id": "353829868653387776"
        },
        {
            "expanded_urls": "",
            "in_reply_to_status_id": "353830828721184768",
            "in_reply_to_user_id": "190470606",
            "retweeted_status_id": "",
            "retweeted_status_timestamp": "",
            "retweeted_status_user_id": "",
            "source": "<a href=\"http://www.justsystems.com/jp/products/tweetatok/\" rel=\"nofollow\">Tweet ATOK</a>",
            "text": "@pathos95606 -ish \u3068\u3044\u3048\u3070\u300c\u8102\u30ae\u30c3\u30b7\u30e5\u300d\u3068\u3044\u3046\u306e\u3092\u601d\u3044\u51fa\u3057\u307e\u3057\u305f\u3002\u3042\u308c\u306f\u300c\u3042\u3076\u3089\u304e\u3063\u3066\u308b\u300d\u306e\u3088\u3046\u306b\u4fc3\u97f3\u306e\u30d9\u30fc\u30b9\u304c\u3042\u3063\u305f\u304b\u3089\u304b\u3082\u3057\u308c\u307e\u305b\u3093\u3002\u78ba\u304b\u306b\u3001\u548c\u88fd\u82f1\u8a9e\u306e\u6d3e\u751f\u6cd5\u3068\u3044\u3046\u306e\u306f\u9762\u767d\u3044\u30c6\u30fc\u30de\u3067\u3059\u306d\u3002",
            "timestamp": "2013-07-07 11:04:59 +0000",
            "tweet_id": "353832008922836992"
        },
        {
            "expanded_urls": "",
            "in_reply_to_status_id": "353836227008532481",
            "in_reply_to_user_id": "270897652",
            "retweeted_status_id": "",
            "retweeted_status_timestamp": "",
            "retweeted_status_user_id": "",
            "source": "<a href=\"http://www.justsystems.com/jp/products/tweetatok/\" rel=\"nofollow\">Tweet ATOK</a>",
            "text": "@nekoworkshop \u30dc\u30c4\u30ea\u30cc\u30b9\u83cc\u304c\u5165\u3063\u3066\u3044\u308b\u3053\u3068\u304c\u3042\u308b\u305d\u3046\u3067\u3002\u59bb\u306f\u30cf\u30c1\u30df\u30c4\u304c\u5371\u967a\u3060\u306a\u3093\u3066\u8003\u3048\u3082\u3057\u3066\u3044\u306a\u304f\u3066\u3001\u307c\u304f\u304c\u8a00\u3063\u3066\u3082\u6700\u521d\u306f\u534a\u4fe1\u534a\u7591\u3067\u3001\u30cd\u30c3\u30c8\u306e\u60c5\u5831\u3092\u898b\u305b\u3066\u521d\u3081\u3066\u7d0d\u5f97\u3057\u305f\u69d8\u5b50\u3002\u666e\u6bb5\u306f\u885b\u661f\u306b\u6c17\u3092\u3064\u3051\u3066\u3044\u308b\u306e\u306b\u3002",
            "timestamp": "2013-07-07 11:32:24 +0000",
            "tweet_id": "353838910155145217"
        },
        {
            "expanded_urls": "",
            "in_reply_to_status_id": "",
            "in_reply_to_user_id": "",
            "retweeted_status_id": "",
            "retweeted_status_timestamp": "",
            "retweeted_status_user_id": "",
            "source": "<a href=\"http://www.justsystems.com/jp/products/tweetatok/\" rel=\"nofollow\">Tweet ATOK</a>",
            "text": "\u3042\u3001\u30ea\u30d7\u30e9\u30a4\u306b\u8aa4\u5b57\u304c\u2026\u3002",
            "timestamp": "2013-07-07 12:02:35 +0000",
            "tweet_id": "353846506391998465"
        },
        {
            "expanded_urls": "",
            "in_reply_to_status_id": "353842022018318336",
            "in_reply_to_user_id": "95545495",
            "retweeted_status_id": "",
            "retweeted_status_timestamp": "",
            "retweeted_status_user_id": "",
            "source": "<a href=\"http://www.justsystems.com/jp/products/tweetatok/\" rel=\"nofollow\">Tweet ATOK</a>",
            "text": "@zeeksphere \u500b\u4eba\u7684\u306b\u306f\u3001\u3058\u3063\u304f\u308a\u898b\u3066\u3044\u308b\u308f\u3051\u3067\u306f\u306a\u304f\u3066\u3082\u98a8\u666f\u304c\u6d41\u308c\u3066\u3044\u308b\u3068\u3044\u3046\u611f\u899a\u306f\u5927\u4e8b\u3067\u3001\u30c8\u30f3\u30cd\u30eb\u306e\u591a\u3044\u533a\u9593\u306f\u3064\u307e\u3089\u306a\u3044\u3067\u3059\u3002\u6771\u4eac-\u5927\u962a\u9593\u3067\u3001\u8eca\u4e21\u306e\u7a93\u304c\u5168\u90e8\u9589\u307e\u3063\u3066\u3044\u308b\u4ee3\u308f\u308a\u306b500\u5186\u5b89\u3044\u5e2d\u306a\u3089\u8cb7\u308f\u306a\u3044\u3051\u308c\u3069\u30011000\u5186\u5b89\u3044\u306a\u3089\u8cb7\u3046\u304b\u306a\u3068\u3044\u3046\u7a0b\u5ea6\u3002",
            "timestamp": "2013-07-07 12:10:36 +0000",
            "tweet_id": "353848519989276672"
        },
        {
            "expanded_urls": "",
            "in_reply_to_status_id": "353848365399805953",
            "in_reply_to_user_id": "270897652",
            "retweeted_status_id": "",
            "retweeted_status_timestamp": "",
            "retweeted_status_user_id": "",
            "source": "<a href=\"http://www.justsystems.com/jp/products/tweetatok/\" rel=\"nofollow\">Tweet ATOK</a>",
            "text": "@nekoworkshop \u306a\u308b\u307b\u3069\u3001\u305d\u308c\u3067\u5927\u4e08\u592b\u3068\u3044\u3046\u601d\u3044\u8fbc\u307f\u304c\u3042\u308b\u306e\u304b\u306a\u3002\u305d\u306e\u96d1\u8a8c\u306f\u65e5\u672c\u306e\u3082\u306e\uff1f",
            "timestamp": "2013-07-07 12:11:56 +0000",
            "tweet_id": "353848856196296704"
        },
        {
            "expanded_urls": "",
            "in_reply_to_status_id": "353852198909775872",
            "in_reply_to_user_id": "270897652",
            "retweeted_status_id": "",
            "retweeted_status_timestamp": "",
            "retweeted_status_user_id": "",
            "source": "<a href=\"http://sites.google.com/site/yorufukurou/\" rel=\"nofollow\">YoruFukurou</a>",
            "text": "@nekoworkshop \u3078\u3047\u3047\u3002\u305d\u308c\u306a\u3089\u3001\u6700\u8fd1\u306f\u4e2d\u56fd\u3067\u3082\u77e5\u3089\u308c\u308b\u3088\u3046\u306b\u306a\u3063\u3066\u304d\u3066\u3044\u308b\u3068\u3044\u3046\u3053\u3068\u304b\u306a\u3002\u307e\u3042\u3001\u65b0\u3057\u3044\u3082\u306e\u3092\u3042\u3052\u308b\u3068\u304d\u306b\u306f\u8abf\u3079\u3066\u304b\u3089\u306e\u307b\u3046\u304c\u3044\u3044\u306d\u3002",
            "timestamp": "2013-07-07 12:30:37 +0000",
            "tweet_id": "353853558250156032"
        },
        {
            "expanded_urls": "",
            "in_reply_to_status_id": "",
            "in_reply_to_user_id": "",
            "retweeted_status_id": "353787261365657600",
            "retweeted_status_timestamp": "2013-07-07 08:07:10 +0000",
            "retweeted_status_user_id": "1255740066",
            "source": "<a href=\"http://www.justsystems.com/jp/products/tweetatok/\" rel=\"nofollow\">Tweet ATOK</a>",
            "text": "RT @tama__komoji: \u300c\u30ef\u30f3\u30c1\u30e3\u30f3\u306e\u70ba\u306e\u30db\u30c6\u30eb\u300d\u3068\u3044\u3046\u770b\u677f\u3092\u898b\u3066\u5199\u771f\u3092\u898b\u308b\u307e\u3067\u72ac\u306e\u3053\u3068\u3060\u3068\u6c17\u3065\u304b\u306a\u304b\u3063\u305f\u5927\u5b66\u751f\u306f\u3053\u3061\u3089\u3067\u3059",
            "timestamp": "2013-07-07 13:19:09 +0000",
            "tweet_id": "353865774592573440"
        },
        {
            "expanded_urls": "http://www.google.co.jp/trends/explore?q=Google%2B,mixi#q=Google%2B%2C%20mixi&date=today%2012-m&cmpt=q",
            "in_reply_to_status_id": "",
            "in_reply_to_user_id": "",
            "retweeted_status_id": "",
            "retweeted_status_timestamp": "",
            "retweeted_status_user_id": "",
            "source": "<a href=\"http://sites.google.com/site/yorufukurou/\" rel=\"nofollow\">YoruFukurou</a>",
            "text": "\u691c\u7d22\u30c8\u30ec\u30f3\u30c9\u3067 Google+ \u304c mixi \u306b\u8ffd\u3044\u4ed8\u304d\u305d\u3046 http://t.co/AoeocWiDGk",
            "timestamp": "2013-07-07 14:35:49 +0000",
            "tweet_id": "353885065689829377"
        },
        {
            "expanded_urls": "",
            "in_reply_to_status_id": "",
            "in_reply_to_user_id": "",
            "retweeted_status_id": "353797809587224577",
            "retweeted_status_timestamp": "2013-07-07 08:49:05 +0000",
            "retweeted_status_user_id": "1183141531",
            "source": "<a href=\"http://sites.google.com/site/yorufukurou/\" rel=\"nofollow\">YoruFukurou</a>",
            "text": "RT @mojibake_bot: \uff7b\uff63\u7e3a\uff6f\u7e32\u221a\u30ef\u7e5d\uff7c\u7e5d\u5ce8\u3048\u7e67\uff67\u7e67\uff62\u8373\u7feb\ufffd\u8b41\ufffd\uff6d\u601c\u55a7\u7e3a\u4ee3\u2032\u9b06\uff7b\u900b\uff7a\u7e3a\u52b1\u25c6\u7e32\u7e67\uff64\u7e5d\uff73\u7e67\uff7f\u7e5d\uff7c\u7e5d\u962a\u30e3\u7e5d\u7e3a\uff6e\u8b4e\uff6e\u873f\u96c1\uff7e\u5f8c\ufffd\u7e67\uff7d\u7e5d\u8f14\u30e8\u7e67\uff66\u7e67\uff67\u7e67\uff62\u7e3a\uff6b\u894d\uff77\u8757\u7e3a\u5436\uff4b\u8b41\ufffd\uff6d\u601c\u55a7\u7e3a\u4ee3\u2032\u879f\u58f9\uffe5\u7e3a\uff6a\u7e3a\uff63\u7e3a\uff66\u7e3a\ufffd\uff4b\u7e32",
            "timestamp": "2013-07-07 15:56:35 +0000",
            "tweet_id": "353905392075546624"
        },
        {
            "expanded_urls": "",
            "in_reply_to_status_id": "",
            "in_reply_to_user_id": "",
            "retweeted_status_id": "353919733407559680",
            "retweeted_status_timestamp": "2013-07-07 16:53:34 +0000",
            "retweeted_status_user_id": "557844536",
            "source": "<a href=\"http://twitter.com/#!/download/ipad\" rel=\"nofollow\">Twitter for iPad</a>",
            "text": "RT @bd_gfngfn: \u8a9e\u5b66\u3092\u3084\u3089\u305a\u306b\u3057\u3070\u3089\u304f\u7d4c\u3064\u3068\uff0c\u6587\u6cd5\u306f\u3088\u304f\u308f\u304b\u3063\u3066\u3044\u308b\u306e\u306b\u5358\u8a9e\u304c\u3069\u3093\u3069\u3093\u629c\u3051\u843d\u3061\u3066\u3044\u308b\u3053\u3068\u306b\u6c17\u3065\u304f",
            "timestamp": "2013-07-07 22:29:33 +0000",
            "tweet_id": "354004285954080768"
        },
        {
            "expanded_urls": "",
            "in_reply_to_status_id": "",
            "in_reply_to_user_id": "",
            "retweeted_status_id": "353989506296320000",
            "retweeted_status_timestamp": "2013-07-07 21:30:49 +0000",
            "retweeted_status_user_id": "15513450",
            "source": "<a href=\"http://twitter.com/#!/download/ipad\" rel=\"nofollow\">Twitter for iPad</a>",
            "text": "RT @cacaho: \u30e4\u30de\u30c8\u306e\u914d\u9001\u3001\u8377\u7269\u304c\u5c4a\u304f\u524d\u306b\u30e1\u30fc\u30eb\u304c\u6765\u3066\u914d\u9001\u65e5\u3092\u6307\u5b9a\u3067\u304d\u308b\u306e\u306f\u3042\u308a\u304c\u305f\u3044\u3093\u3060\u3051\u3069\u3001\u73fe\u6642\u70b9\u3067\u3044\u3064\u306a\u3089\u53d7\u3051\u53d6\u308c\u305d\u3046\u304b\u5206\u304b\u3089\u306a\u3044\u3068\u914d\u9001\u65e5\u3092\u6307\u5b9a\u3067\u304d\u305a\u3001\u5bb6\u306b\u4f55\u5ea6\u3082\u6301\u3063\u3066\u6765\u3066\u3082\u3089\u3046\u3053\u3068\u306b\u306a\u3063\u3066\u3057\u307e\u3044\u7533\u3057\u8a33\u306a\u3044\u306e\u3067\u3001\u300e\u4eca\u65e5\u306f\u6301\u3063\u3066\u3053\u306a\u304f\u3066\u826f\u3044\u3067\u3059\u300f\u30dc\u30bf\u30f3\u304c\u307b\u3057\u3044\u2026",
            "timestamp": "2013-07-07 22:33:50 +0000",
            "tweet_id": "354005363449802752"
        },
        {
            "expanded_urls": "",
            "in_reply_to_status_id": "",
            "in_reply_to_user_id": "",
            "retweeted_status_id": "",
            "retweeted_status_timestamp": "",
            "retweeted_status_user_id": "",
            "source": "<a href=\"http://www.justsystems.com/jp/products/tweetatok/\" rel=\"nofollow\">Tweet ATOK</a>",
            "text": "\u30c6\u30ec\u30d3\u3067\u300c\u5973\u6027\u529b\u3092\u6d3b\u7528\u3059\u308b\u300d\u3068\u304b\u8a00\u3063\u3066\u3066\u3001\u5973\u6027\u529b\u3068\u5973\u5b50\u529b\u3067\u306f\u5927\u9055\u3044\u3060\u306a\u30fc\u3068\u601d\u3046\u306a\u3069",
            "timestamp": "2013-07-07 22:36:10 +0000",
            "tweet_id": "354005952204247041"
        }
    ]
}