{
    "date": "2014-12-13",
    "items": [
        {
            "expanded_urls": "",
            "in_reply_to_status_id": "",
            "in_reply_to_user_id": "",
            "retweeted_status_id": "543467113159983104",
            "retweeted_status_timestamp": "2014-12-12 18:07:11 +0000",
            "retweeted_status_user_id": "4426821",
            "source": "<a href=\"http://twitter.com/#!/download/ipad\" rel=\"nofollow\">Twitter for iPad</a>",
            "text": "RT @fuba: \u30a2\u30e0\u30a6\u30a7\u30a4\u3082\u30dd\u30eb\u30ce\u30a2\u30cb\u30e1\u3092\u58f2\u308c\u3070\u3088\u3044",
            "timestamp": "2014-12-13 00:22:44 +0000",
            "tweet_id": "543561622841589762"
        },
        {
            "expanded_urls": "",
            "in_reply_to_status_id": "",
            "in_reply_to_user_id": "",
            "retweeted_status_id": "",
            "retweeted_status_timestamp": "",
            "retweeted_status_user_id": "",
            "source": "<a href=\"http://twitter.com/#!/download/ipad\" rel=\"nofollow\">Twitter for iPad</a>",
            "text": "575\u3060",
            "timestamp": "2014-12-13 00:22:53 +0000",
            "tweet_id": "543561659592085504"
        },
        {
            "expanded_urls": "",
            "in_reply_to_status_id": "",
            "in_reply_to_user_id": "",
            "retweeted_status_id": "543549673756450816",
            "retweeted_status_timestamp": "2014-12-12 23:35:15 +0000",
            "retweeted_status_user_id": "126002546",
            "source": "<a href=\"http://twitter.com/#!/download/ipad\" rel=\"nofollow\">Twitter for iPad</a>",
            "text": "RT @OED: The word \"dinner\" ultimately has the same root as French \"d\u00e9jeuner,\" which means \"breakfast.\"",
            "timestamp": "2014-12-13 01:01:55 +0000",
            "tweet_id": "543571483436408832"
        },
        {
            "expanded_urls": "https://twitter.com/harupiyo1582/status/543344802754871297/photo/1,https://twitter.com/harupiyo1582/status/543344802754871297/photo/1",
            "in_reply_to_status_id": "",
            "in_reply_to_user_id": "",
            "retweeted_status_id": "543344802754871297",
            "retweeted_status_timestamp": "2014-12-12 10:01:10 +0000",
            "retweeted_status_user_id": "1655543443",
            "source": "<a href=\"http://twitter.com/#!/download/ipad\" rel=\"nofollow\">Twitter for iPad</a>",
            "text": "RT @harupiyo1582: \u4eca\u65e5\u306e\u897f\u65e5\u672c\u65b0\u805e\u3088\u308a\n\u300c\u5973\u6027\u30a2\u30ca\u30a6\u30f3\u30b5\u30fc\u5185\u5b9a\u53d6\u308a\u6d88\u3057\u300d\u306e\u554f\u984c\u70b9\u304c\u3001\u89e3\u308a\u3084\u3059\u304f\u7684\u78ba\u306b\u8a18\u3055\u308c\u3066\u3044\u307e\u3059\u3002 http://t.co/iknJFl7QBy",
            "timestamp": "2014-12-13 01:23:52 +0000",
            "tweet_id": "543577009180266496"
        },
        {
            "expanded_urls": "",
            "in_reply_to_status_id": "",
            "in_reply_to_user_id": "",
            "retweeted_status_id": "543580802609459200",
            "retweeted_status_timestamp": "2014-12-13 01:38:57 +0000",
            "retweeted_status_user_id": "948770966",
            "source": "<a href=\"http://twitter.com/#!/download/ipad\" rel=\"nofollow\">Twitter for iPad</a>",
            "text": "RT @kuroimame3: \u56fd\u8a9e\u306e\u6559\u79d1\u66f8\u3067\u7fd2\u3063\u305f\u300c\u300e\u3042\u308a\u304c\u3068\u3046\u300f\u3068\u8a00\u308f\u306a\u3044\u91cd\u3055\u300d\u3092\u601d\u3044\u51fa\u3057\u305f\u3002\u30e2\u30f3\u30b4\u30eb\u8a9e\u306b\u300c\u3042\u308a\u304c\u3068\u3046\u300d\u306b\u3042\u305f\u308b\u8a00\u8449\u306f\u3042\u308b\u3051\u3069\u3001\u6ec5\u591a\u306b\u8a00\u308f\u306a\u3044\u3068\u304b\u3002\u884c\u52d5\u3067\u793a\u3055\u306a\u3044\u3068\u5931\u793c\u3060\u304b\u3089\u3068\u304b\u306a\u3093\u3068\u304b\u3002\u305d\u308c\u3063\u3066\u300c\u3042\u308a\u304c\u3068\u3046\u300d\u306b\u3042\u305f\u308b\u8a00\u8449\u304c\u306a\u3044\u3063\u3066\u89e3\u91c8\u3067\u3082\u3044\u3044\u3088\u3046\u306a\u3002",
            "timestamp": "2014-12-13 02:06:48 +0000",
            "tweet_id": "543587812071579648"
        },
        {
            "expanded_urls": "",
            "in_reply_to_status_id": "",
            "in_reply_to_user_id": "",
            "retweeted_status_id": "",
            "retweeted_status_timestamp": "",
            "retweeted_status_user_id": "",
            "source": "<a href=\"http://twitter.com/#!/download/ipad\" rel=\"nofollow\">Twitter for iPad</a>",
            "text": "\u305d\u3046\u3044\u3048\u3070\u3001\u4e2d\u56fd\u8a9e\u3067\u306f\u5bb6\u65cf\u5185\u3067\u8b1d\u8b1d\u3068\u8a00\u3048\u306a\u3044\u306e\u3067\u3001\u307c\u304f\u306f\u59bb\u3068\u4e2d\u56fd\u8a9e\u3067\u3057\u3083\u3079\u3063\u3066\u3044\u3066\u3082\u3042\u308a\u304c\u3068\u3046\u3060\u3051\u65e5\u672c\u8a9e\u3067\u8a00\u3046\u3002\uff08\u611f\u8b1d\u8868\u73fe\u3092\u3059\u308b\u304b\u3057\u306a\u3044\u304b\u306e\u57fa\u6e96\u3092\u666e\u6bb5\u3068\u5909\u3048\u308b\u3088\u308a\u305d\u306e\u307b\u3046\u304c\u697d\uff09",
            "timestamp": "2014-12-13 02:08:58 +0000",
            "tweet_id": "543588355733073921"
        },
        {
            "expanded_urls": "",
            "in_reply_to_status_id": "",
            "in_reply_to_user_id": "",
            "retweeted_status_id": "543582612950769664",
            "retweeted_status_timestamp": "2014-12-13 01:46:08 +0000",
            "retweeted_status_user_id": "15312900",
            "source": "<a href=\"http://twitter.com/#!/download/ipad\" rel=\"nofollow\">Twitter for iPad</a>",
            "text": "RT @chokudai: \u300c\u307f\u306a\u307f\u3051\u3068\u3088\u3064\u3070\u3068\u3068\u3089\u304d\u3059\u305f\u3063\u3066\u4f55\u304c\u9055\u3046\u306e\uff1f\u300d\u3063\u3066\u805e\u304b\u308c\u305f\u306e\u3067\u3001\u300c\u4f55\u3082\u3064\u3044\u3066\u306a\u3044\u306e\u304c\u300e\u307f\u306a\u307f\u3051\u300f\u3001\u6700\u5f8c\u306b\uff01\u304c\u3064\u3044\u3066\u308b\u306e\u304c\u300e\u3088\u3064\u3070\u3068\uff01\u300f\u3001\u771f\u3093\u4e2d\u306b\u2606\u304c\u3064\u3044\u3066\u308b\u306e\u304c\u300e\u3089\u304d\u2606\u3059\u305f\u300f\u3060\u3088\u3063\u3066\u8aac\u660e\u3057\u305f\u3051\u3069\u5408\u3063\u3066\u308b\u3088\u306d\uff1f",
            "timestamp": "2014-12-13 02:09:50 +0000",
            "tweet_id": "543588576932270080"
        },
        {
            "expanded_urls": "",
            "in_reply_to_status_id": "",
            "in_reply_to_user_id": "",
            "retweeted_status_id": "543582652683386880",
            "retweeted_status_timestamp": "2014-12-13 01:46:18 +0000",
            "retweeted_status_user_id": "15312900",
            "source": "<a href=\"http://twitter.com/#!/download/ipad\" rel=\"nofollow\">Twitter for iPad</a>",
            "text": "RT @chokudai: \u3064\u30fc\u304b\u4f55\u3082\u304b\u3082\u9055\u3046\u308f",
            "timestamp": "2014-12-13 02:09:53 +0000",
            "tweet_id": "543588586994409474"
        },
        {
            "expanded_urls": "",
            "in_reply_to_status_id": "",
            "in_reply_to_user_id": "",
            "retweeted_status_id": "543590508421865472",
            "retweeted_status_timestamp": "2014-12-13 02:17:31 +0000",
            "retweeted_status_user_id": "13902442",
            "source": "<a href=\"http://twitter.com/#!/download/ipad\" rel=\"nofollow\">Twitter for iPad</a>",
            "text": "RT @asaokitan: \u6700\u8fd1\u51fa\u305f\u300e\u3082\u306e\u306e\u8a00\u3044\u304b\u305f\u897f\u6771\u300f\u3068\u3044\u3046\u672c\u306b\u3088\u308c\u3070\u56fd\u5185\u3067\u3082\u6328\u62f6\u8868\u73fe\u3092\u4f7f\u3046\u304b\u3069\u3046\u304b\u306f\u304b\u306a\u308a\u5dee\u304c\u3042\u308b\u3089\u3057\u3044\u306d\u3002\u5bb6\u5ead\u5185\u3067\u306f\u300c\u3042\u308a\u304c\u3068\u3046\u300d\u3068\u8a00\u308f\u306a\u3044\u50be\u5411\u306f\u6771\u5317\u3067\u5f37\u3044\u3089\u3057\u3044\u3002",
            "timestamp": "2014-12-13 02:24:47 +0000",
            "tweet_id": "543592338367332353"
        },
        {
            "expanded_urls": "",
            "in_reply_to_status_id": "",
            "in_reply_to_user_id": "",
            "retweeted_status_id": "543590890036424704",
            "retweeted_status_timestamp": "2014-12-13 02:19:02 +0000",
            "retweeted_status_user_id": "1359661616",
            "source": "<a href=\"http://twitter.com/#!/download/ipad\" rel=\"nofollow\">Twitter for iPad</a>",
            "text": "RT @minorimironim: \u300c\u6700\u8fd1\u300d\u306f\u308f\u308a\u3068\u5e83\u3044\u30b9\u30d1\u30f3\u3067\u4f7f\u3048\u3066\u3001\u4f8b\u3048\u3070\u300c\u6587\u5b57\u304c\u5c0e\u5165\u3055\u308c\u305f\u306e\u306f\uff08\u8a00\u8a9e\u306e\u767a\u751f\u304b\u3089\u8003\u3048\u308b\u3068\uff09\u3054\u304f\u6700\u8fd1\u306e\u3053\u3068\u3060\u300d\u3068\u8a00\u3048\u308b\u6c17\u304c\u3057\u307e\u3059\u304c\u3001\u300c\u6700\u3082\u8fd1\u3044\u300d\u3068\u3044\u3046\u5b57\u9762\u306b\u53cd\u3057\u3066\u3001\u6628\u65e5\u306e\u3053\u3068 \uff08\u306a\u3093\u3060\u3063\u305f\u30895\u5206\u524d\u306e\u307b\u3046\u304c\u3088\u308a\u8fd1\u3044\u306e\u306b\uff09 \u306b\u306f\u975e\u5e38\u306b\u4f7f\u3044\u306b\u304f\u3044\u306e\u2026",
            "timestamp": "2014-12-13 02:26:30 +0000",
            "tweet_id": "543592768338026496"
        },
        {
            "expanded_urls": "",
            "in_reply_to_status_id": "",
            "in_reply_to_user_id": "",
            "retweeted_status_id": "",
            "retweeted_status_timestamp": "",
            "retweeted_status_user_id": "",
            "source": "<a href=\"http://twitter.com/#!/download/ipad\" rel=\"nofollow\">Twitter for iPad</a>",
            "text": "\u6700\u8fd1\u3063\u3066\u3069\u308c\u3050\u3089\u3044\u8fd1\u3044\u904e\u53bb\u307e\u3067\u6307\u305b\u308b\u3093\u3060\u308d\u3046\u3002\u30b2\u30fc\u30e0\u30925\u6642\u9593\u3050\u3089\u3044\u3084\u3063\u3066\u3066\u3001\u6700\u521d\u306e2\u6642\u9593\u3050\u3089\u3044\u3088\u304f\u51fa\u308b\u6575\u304c\u3044\u305f\u306e\u306b\u7d42\u76e4\u3067\u3042\u3093\u307e\u308a\u51fa\u306a\u304f\u306a\u3063\u305f\u3089\u300c\u3053\u306e\u6575\u6700\u8fd1\u3042\u3093\u307e\u308a\u51fa\u3066\u3053\u306a\u3044\u306a\u300d\u3068\u304b\u8a00\u3048\u308b\u304b\u306a\uff1f\uff08\u7121\u7406\u304c\u3042\u308b\u304b\u306a\uff09",
            "timestamp": "2014-12-13 02:29:03 +0000",
            "tweet_id": "543593409844215810"
        },
        {
            "expanded_urls": "",
            "in_reply_to_status_id": "",
            "in_reply_to_user_id": "",
            "retweeted_status_id": "543594671914496000",
            "retweeted_status_timestamp": "2014-12-13 02:34:03 +0000",
            "retweeted_status_user_id": "1359661616",
            "source": "<a href=\"http://twitter.com/#!/download/ipad\" rel=\"nofollow\">Twitter for iPad</a>",
            "text": "RT @minorimironim: \u4f8b\u3048\u3070\u30b2\u30fc\u30e0\u5185\u3060\u304b\u3089\u6642\u9593\u306e\u9032\u884c\u304c\u901f\u304f\u300124\u6642\u9593\u3067\u4eba\u306e\u4e00\u751f\u304c\u7d42\u308f\u308b\u3068\u3057\u3066\u3082\u3001\u300c\u6700\u8fd1\u300d\u3092\u4f7f\u3046\u306b\u306f\u300c\u767b\u5834\u4eba\u7269\u306e\u7acb\u5834\u3067\u306f\u300d\u3068\u304b\u6795\u3092\u3064\u3051\u306a\u3044\u3068\u53b3\u3057\u3044\u611f\u3058\u304c\u3059\u308b\u3093\u3067\u3059\u3088\u306d\u3002\u9577\u3044\u307b\u3046\u3060\u3068\u5358\u72ec\u3067\u3082\u3001\u4f8b\u3048\u3070\u300c\u795e\u306e\u8996\u70b9\u304b\u3089\u306f\u300d\u3068\u304b\u7121\u3057\u3067\u4f7f\u3048\u305d\u3046\u3002",
            "timestamp": "2014-12-13 02:34:34 +0000",
            "tweet_id": "543594799803019264"
        },
        {
            "expanded_urls": "",
            "in_reply_to_status_id": "",
            "in_reply_to_user_id": "",
            "retweeted_status_id": "",
            "retweeted_status_timestamp": "",
            "retweeted_status_user_id": "",
            "source": "<a href=\"http://twitter.com/#!/download/ipad\" rel=\"nofollow\">Twitter for iPad</a>",
            "text": "\u6587\u8a9e\u3067\u540d\u8a5e\u3068\u3057\u3066\u300c\u4eba\u985e\u304c\u751f\u307e\u308c\u305f\u306e\u306f\u3054\u304f\u6700\u8fd1\u306e\u3053\u3068\u3060\u300d\u307f\u305f\u3044\u306b\u8a00\u3048\u308b\u3051\u3069\u3001\u53e3\u8a9e\u306e\u526f\u8a5e\u3067\u300c\u4eba\u985e\u3063\u3066\u6700\u8fd1\u77f3\u5668\u4f7f\u308f\u306a\u3044\u3088\u306d\u301c\u300d\u3068\u304b\u8a00\u3048\u308b\u304b\u306a\uff08\u610f\u5473\u7684\u306b\u7121\u7406\u304c\u3042\u308b\uff09\uff08\u3051\u3069\u8a00\u3048\u308b\u304b\uff09",
            "timestamp": "2014-12-13 02:40:13 +0000",
            "tweet_id": "543596221055508480"
        },
        {
            "expanded_urls": "",
            "in_reply_to_status_id": "",
            "in_reply_to_user_id": "",
            "retweeted_status_id": "",
            "retweeted_status_timestamp": "",
            "retweeted_status_user_id": "",
            "source": "<a href=\"http://twitter.com/#!/download/ipad\" rel=\"nofollow\">Twitter for iPad</a>",
            "text": "overbrigde\u3001\u751f\u6d3b\u611f\u899a\u3068\u3044\u3046\u6c17\u304c\u3059\u308b\uff08\u82f1\u8a9e\u8a71\u8005\u306f\u3042\u307e\u308a\u5ddd\u306e\u6a4b\u304c\u81ea\u5206\u306e\u4e0a\u306b\u3042\u308b\u3068\u3044\u3046\u72b6\u6cc1\u306b\u306a\u3089\u306a\u3044\u306e\u3067\u3042\u308d\u3046\uff09",
            "timestamp": "2014-12-13 02:52:39 +0000",
            "tweet_id": "543599350379577344"
        },
        {
            "expanded_urls": "",
            "in_reply_to_status_id": "",
            "in_reply_to_user_id": "",
            "retweeted_status_id": "",
            "retweeted_status_timestamp": "",
            "retweeted_status_user_id": "",
            "source": "<a href=\"http://twitter.com/#!/download/ipad\" rel=\"nofollow\">Twitter for iPad</a>",
            "text": "\u4e2d\u56fd\u8a9e\u3067\u306f\u5929\u6a4b",
            "timestamp": "2014-12-13 02:55:40 +0000",
            "tweet_id": "543600108093198337"
        },
        {
            "expanded_urls": "",
            "in_reply_to_status_id": "",
            "in_reply_to_user_id": "",
            "retweeted_status_id": "",
            "retweeted_status_timestamp": "",
            "retweeted_status_user_id": "",
            "source": "<a href=\"http://twitter.com/#!/download/ipad\" rel=\"nofollow\">Twitter for iPad</a>",
            "text": "\u663c\u98df\u306b\u5bb6\u306e\u30ab\u30ec\u30fc\u3092\u98df\u3079\u3066\u304b\u3089\u4eac\u90fd\u306b\u884c\u304f\u304b\u3001\u96e3\u6ce2\u306b\u884c\u3063\u3066\u4e16\u754c\u6700\u9ad8\u306e\u7f8e\u98df\u30b3\u30b3\u30a4\u30c1\u306e\u30ab\u30ec\u30fc\u3092\u98df\u3079\u308b\u304b\u8ff7\u3063\u3066\u3044\u308b\uff08\u3069\u3046\u3067\u3082\u3044\u3044\uff09",
            "timestamp": "2014-12-13 03:07:23 +0000",
            "tweet_id": "543603057582284801"
        },
        {
            "expanded_urls": "",
            "in_reply_to_status_id": "",
            "in_reply_to_user_id": "",
            "retweeted_status_id": "",
            "retweeted_status_timestamp": "",
            "retweeted_status_user_id": "",
            "source": "<a href=\"http://twitter.com/#!/download/ipad\" rel=\"nofollow\">Twitter for iPad</a>",
            "text": "\u4eac\u90fd\u306e\u30de\u30af\u30c9\u3067\u30d3\u30c3\u30b0\u30de\u30c3\u30af\u5206\u306e\u88dc\u7d66\u3068\u3044\u3046\u624b\u3082\u3042\u308b\u306a",
            "timestamp": "2014-12-13 03:08:20 +0000",
            "tweet_id": "543603298024976384"
        },
        {
            "expanded_urls": "",
            "in_reply_to_status_id": "",
            "in_reply_to_user_id": "",
            "retweeted_status_id": "543601335027765249",
            "retweeted_status_timestamp": "2014-12-13 03:00:32 +0000",
            "retweeted_status_user_id": "175424545",
            "source": "<a href=\"http://twitter.com/#!/download/ipad\" rel=\"nofollow\">Twitter for iPad</a>",
            "text": "RT @aadiimmz: \u300c\u6700\u8fd1\u307f\u304b\u3093\u98df\u3079\u305f\uff1f\u300d\u306f5\u5206\u524d\u306b\u98df\u3079\u3066\u3066\u3082\u30a4\u30a8\u30b9\u3068\u7b54\u3048\u308b\u306d\u4ffa\u306f",
            "timestamp": "2014-12-13 03:08:32 +0000",
            "tweet_id": "543603349635887104"
        },
        {
            "expanded_urls": "",
            "in_reply_to_status_id": "",
            "in_reply_to_user_id": "",
            "retweeted_status_id": "",
            "retweeted_status_timestamp": "",
            "retweeted_status_user_id": "",
            "source": "<a href=\"http://twitter.com/#!/download/ipad\" rel=\"nofollow\">Twitter for iPad</a>",
            "text": "\u6700\u8fd1\u306f\u7bc4\u56f2\u3092\u6307\u3059\u304b\u3089\u3001\u4e00\u304b\u6708\u524d\u306b\u98df\u3079\u3066\u3066\u3082\u30a4\u30a8\u30b9\u306b\u306a\u308b\u306a\u3089\u3084\u3063\u3071\u308a\u7d50\u69cb\u524d\u307e\u3067\u6307\u3059\u3068\u3044\u3046\u3053\u3068\u306b\u306a\u308b\u3093\u3058\u3083\u306a\u3044\u304b\u306a",
            "timestamp": "2014-12-13 03:09:47 +0000",
            "tweet_id": "543603662686134273"
        },
        {
            "expanded_urls": "",
            "in_reply_to_status_id": "543603560324558848",
            "in_reply_to_user_id": "158183627",
            "retweeted_status_id": "",
            "retweeted_status_timestamp": "",
            "retweeted_status_user_id": "",
            "source": "<a href=\"http://twitter.com/#!/download/ipad\" rel=\"nofollow\">Twitter for iPad</a>",
            "text": "@ZukashiT \u305d\u308c\u306b\u95a2\u3057\u3066\u306f\u5f37\u304f\u540c\u610f\u3059\u308b\u3068\u3053\u308d\u3067\u3059",
            "timestamp": "2014-12-13 03:10:10 +0000",
            "tweet_id": "543603757641003008"
        },
        {
            "expanded_urls": "",
            "in_reply_to_status_id": "",
            "in_reply_to_user_id": "",
            "retweeted_status_id": "543603658135322624",
            "retweeted_status_timestamp": "2014-12-13 03:09:46 +0000",
            "retweeted_status_user_id": "13902442",
            "source": "<a href=\"http://twitter.com/#!/download/ipad\" rel=\"nofollow\">Twitter for iPad</a>",
            "text": "RT @asaokitan: \u6700\u8fd1\u8a9e\u7528\u8ad6\u306e\u672c\u3067\u300c\u9ad8\u6821\u306e\u3068\u304d\u30d0\u30b9\u30b1\u3084\u3063\u3066\u305f\u3093\u3067\u3057\u3087\uff1f\u300d\u300c\u3042\u3001\u3046\u3093\u3002\u4e2d\u5b66\u306e\u3068\u304d\u3060\u3051\u3069\u306d\u300d\u307f\u305f\u3044\u306a\u4f8b\u3092\u898b\u305f\u306e\u3067\u30a4\u30a7\u30b9\u3067\u7b54\u3048\u3089\u308c\u308b\u3053\u3068\u304c\u4f55\u3092\u610f\u5473\u3057\u3066\u3044\u308b\u306e\u304b\u5206\u304b\u3089\u306a\u3044\u8eab\u4f53\u306b\u306a\u3063\u3066\u3057\u307e\u3063\u305f",
            "timestamp": "2014-12-13 03:10:37 +0000",
            "tweet_id": "543603873684811776"
        },
        {
            "expanded_urls": "",
            "in_reply_to_status_id": "543604215818756097",
            "in_reply_to_user_id": "158183627",
            "retweeted_status_id": "",
            "retweeted_status_timestamp": "",
            "retweeted_status_user_id": "",
            "source": "<a href=\"http://twitter.com/#!/download/ipad\" rel=\"nofollow\">Twitter for iPad</a>",
            "text": "@ZukashiT \u3067\u3059\u306d\u3047\u3002\u30de\u30af\u30c9\u30ca\u30eb\u30c9\u3067\u6ce8\u6587\u3059\u308b\u3068\u304d\u306b\u59bb\u306b\u300c\u4f55\u306b\u3059\u308b\uff1f\u300d\u3068\u805e\u304b\u308c\u305f\u308a\u3059\u308b\u306e\u3067\u3059\u304c\u3001\u3042\u307e\u308a\u306b\u81ea\u660e\u306a\u3053\u3068\u306a\u306e\u3067\u4e00\u77ac\u300c\u3048\u3063\u300d\u3068\u3044\u3046\u53cd\u5fdc\u306b\u306a\u3063\u3066\u3057\u307e\u3044\u307e\u3059\u3002\u307e\u308b\u3067\u307b\u304b\u306b\u9078\u629e\u80a2\u304c\u3042\u308b\u304b\u306e\u3088\u3046\u306a\u3002",
            "timestamp": "2014-12-13 03:15:07 +0000",
            "tweet_id": "543605006834737152"
        },
        {
            "expanded_urls": "",
            "in_reply_to_status_id": "",
            "in_reply_to_user_id": "",
            "retweeted_status_id": "",
            "retweeted_status_timestamp": "",
            "retweeted_status_user_id": "",
            "source": "<a href=\"http://twitter.com/#!/download/ipad\" rel=\"nofollow\">Twitter for iPad</a>",
            "text": "\u307e\u3042\u3067\u3082\u30de\u30af\u30c9\u30ca\u30eb\u30c9\u306f\u8fba\u5883\u661f\u306e\u5de8\u5927\u5efa\u9020\u7269\u306b\u3082\u5165\u3063\u3066\u308b\u304b\u3089\u308f\u3056\u308f\u3056\u6587\u660e\u306e\u5730\u306b\u884c\u3063\u3066\u98df\u3079\u308b\u306e\u306f\u3069\u3046\u304b\u3068\u3044\u3046\u8996\u70b9\u3082\u3042\u308b\u306a",
            "timestamp": "2014-12-13 03:17:27 +0000",
            "tweet_id": "543605591642365952"
        },
        {
            "expanded_urls": "",
            "in_reply_to_status_id": "543605626237353984",
            "in_reply_to_user_id": "158183627",
            "retweeted_status_id": "",
            "retweeted_status_timestamp": "",
            "retweeted_status_user_id": "",
            "source": "<a href=\"http://twitter.com/#!/download/ipad\" rel=\"nofollow\">Twitter for iPad</a>",
            "text": "@ZukashiT \u30a8\u30d3\u30d0\u30fc\u30ac\u30fc\u306b\u3064\u3044\u3066\u306f\u611f\u899a\u3092\u5171\u6709\u3067\u304d\u306a\u3044\u3067\u3059\u306d\u2026\uff08\u9b5a\u4ecb\u985e\u82e6\u624b\uff09",
            "timestamp": "2014-12-13 03:18:37 +0000",
            "tweet_id": "543605886128635905"
        },
        {
            "expanded_urls": "",
            "in_reply_to_status_id": "543606529271017472",
            "in_reply_to_user_id": "158183627",
            "retweeted_status_id": "",
            "retweeted_status_timestamp": "",
            "retweeted_status_user_id": "",
            "source": "<a href=\"http://twitter.com/#!/download/ipad\" rel=\"nofollow\">Twitter for iPad</a>",
            "text": "@ZukashiT \u305d\u3046\u3067\u3059\u306d\u3001\u305d\u3082\u305d\u3082\u884c\u304b\u306a\u3044\u3067\u3059\u306d\u3002",
            "timestamp": "2014-12-13 03:21:30 +0000",
            "tweet_id": "543606611789377536"
        },
        {
            "expanded_urls": "",
            "in_reply_to_status_id": "",
            "in_reply_to_user_id": "",
            "retweeted_status_id": "",
            "retweeted_status_timestamp": "",
            "retweeted_status_user_id": "",
            "source": "<a href=\"http://twitter.com/#!/download/ipad\" rel=\"nofollow\">Twitter for iPad</a>",
            "text": "\u307e\u3042\u4eca\u65e5\u306f\u65e5\u548c\u3063\u3066\u5bb6\u30ab\u30ec\u30fc\u306b\u3057\u3088\u3046\uff08\u5915\u98df\u3082\uff09",
            "timestamp": "2014-12-13 03:23:47 +0000",
            "tweet_id": "543607184676769794"
        },
        {
            "expanded_urls": "",
            "in_reply_to_status_id": "",
            "in_reply_to_user_id": "",
            "retweeted_status_id": "543610516544180224",
            "retweeted_status_timestamp": "2014-12-13 03:37:01 +0000",
            "retweeted_status_user_id": "30661059",
            "source": "<a href=\"http://twitter.com/#!/download/ipad\" rel=\"nofollow\">Twitter for iPad</a>",
            "text": "RT @Scaled_Wurm: \u8089\u4f53\u306e\u64cd\u4f5c\u304c\u82e6\u624b(\u8db3\u3068\u304b\u3092\u3088\u304f\u3076\u3064\u3051\u308b",
            "timestamp": "2014-12-13 03:41:44 +0000",
            "tweet_id": "543611704165142530"
        },
        {
            "expanded_urls": "",
            "in_reply_to_status_id": "",
            "in_reply_to_user_id": "",
            "retweeted_status_id": "",
            "retweeted_status_timestamp": "",
            "retweeted_status_user_id": "",
            "source": "<a href=\"http://twitter.com/#!/download/ipad\" rel=\"nofollow\">Twitter for iPad</a>",
            "text": "\u3042\u308b",
            "timestamp": "2014-12-13 03:41:49 +0000",
            "tweet_id": "543611723110830081"
        },
        {
            "expanded_urls": "",
            "in_reply_to_status_id": "",
            "in_reply_to_user_id": "",
            "retweeted_status_id": "",
            "retweeted_status_timestamp": "",
            "retweeted_status_user_id": "",
            "source": "<a href=\"http://twitter.com/#!/download/ipad\" rel=\"nofollow\">Twitter for iPad</a>",
            "text": "\u30a2\u30af\u30c6\u30a3\u30d6\u306a\u4eba\u9593\u3060\u304b\u3089\u4eac\u90fd\u306e\u672c\u5c4b\u306b\u884c\u304f\uff08\u307c\u304f\u306f\u4f55\u306e\u305f\u3081\u306b\u81ea\u5206\u304c\u30a2\u30af\u30c6\u30a3\u30d6\u306a\u4eba\u9593\u3060\u3068\u3044\u3046\u30a2\u30d4\u30fc\u30eb\u3092\u3057\u3066\u3044\u308b\u3093\u3060\u308d\u3046\uff09\uff08\u9577\u5e74\u306e\u7fd2\u6027\uff09",
            "timestamp": "2014-12-13 03:48:29 +0000",
            "tweet_id": "543613402803732480"
        },
        {
            "expanded_urls": "",
            "in_reply_to_status_id": "",
            "in_reply_to_user_id": "",
            "retweeted_status_id": "",
            "retweeted_status_timestamp": "",
            "retweeted_status_user_id": "",
            "source": "<a href=\"http://twitter.com/download/iphone\" rel=\"nofollow\">Twitter for iPhone</a>",
            "text": "\u6bce\u9031\u3069\u3053\u304b\u306e\u4f1a\u5834\u3067\u4f55\u3089\u304b\u306e\u7bb1\u306b\u4f55\u3089\u304b\u306e\u7d19\u3092\u5165\u308c\u308b\u30a4\u30d9\u30f3\u30c8\u304c\u3042\u3063\u3066\u6bce\u9031\u62db\u5f85\u72b6\u304c\u5c4a\u304f\u3068\u3057\u305f\u3089\u4f55\u9031\u9593\u306b\u4e00\u56de\u3050\u3089\u3044\u884c\u304f\u3082\u306e\u306a\u3093\u3060\u308d\u3046",
            "timestamp": "2014-12-13 04:07:04 +0000",
            "tweet_id": "543618079045853184"
        },
        {
            "expanded_urls": "",
            "in_reply_to_status_id": "",
            "in_reply_to_user_id": "",
            "retweeted_status_id": "543614204855349248",
            "retweeted_status_timestamp": "2014-12-13 03:51:40 +0000",
            "retweeted_status_user_id": "1359661616",
            "source": "<a href=\"http://twitter.com/download/iphone\" rel=\"nofollow\">Twitter for iPhone</a>",
            "text": "RT @minorimironim: \u7cbe\u795e\u306e\u64cd\u4f5c\u304c\u82e6\u624b\uff08\u4eba\u3068\u304b\u306b\u3088\u304f\u3076\u3064\u304b\u308b",
            "timestamp": "2014-12-13 04:07:29 +0000",
            "tweet_id": "543618182074732545"
        },
        {
            "expanded_urls": "",
            "in_reply_to_status_id": "",
            "in_reply_to_user_id": "",
            "retweeted_status_id": "",
            "retweeted_status_timestamp": "",
            "retweeted_status_user_id": "",
            "source": "<a href=\"http://twitter.com/download/iphone\" rel=\"nofollow\">Twitter for iPhone</a>",
            "text": "\u30d6\u30ae\u30fc\u30dc\u30fc\u30c9\u304c\u30c8\u30a4\u30b6\u3089\u30b9\u306b\u6d41\u308c\u7740\u3044\u3066\u3044\u308b",
            "timestamp": "2014-12-13 04:59:31 +0000",
            "tweet_id": "543631277715226624"
        },
        {
            "expanded_urls": "http://youtu.be/a35NLJv_BoI?list=PLq_92tiIzpE-GAmgbpYqqvD6J1IyTcaXV,http://youtu.be/a35NLJv_BoI?list=PLq_92tiIzpE-GAmgbpYqqvD6J1IyTcaXV",
            "in_reply_to_status_id": "",
            "in_reply_to_user_id": "",
            "retweeted_status_id": "543625679984529408",
            "retweeted_status_timestamp": "2014-12-13 04:37:16 +0000",
            "retweeted_status_user_id": "14919778",
            "source": "<a href=\"http://twitter.com/download/iphone\" rel=\"nofollow\">Twitter for iPhone</a>",
            "text": "RT @mandel59: TARAKO: http://t.co/pWgYwGs75t @YouTube\u3055\u3093\u304b\u3089",
            "timestamp": "2014-12-13 05:07:18 +0000",
            "tweet_id": "543633237311229953"
        },
        {
            "expanded_urls": "",
            "in_reply_to_status_id": "",
            "in_reply_to_user_id": "",
            "retweeted_status_id": "",
            "retweeted_status_timestamp": "",
            "retweeted_status_user_id": "",
            "source": "<a href=\"http://twitter.com/download/iphone\" rel=\"nofollow\">Twitter for iPhone</a>",
            "text": "\u30d6\u30ae\u30fc\u30dc\u30fc\u30c9\u3001\u8150\u3089\u305b\u3066\u3057\u307e\u3063\u305f\u82e6\u3044\u7d4c\u9a13\u304c",
            "timestamp": "2014-12-13 05:20:09 +0000",
            "tweet_id": "543636471924523009"
        },
        {
            "expanded_urls": "",
            "in_reply_to_status_id": "",
            "in_reply_to_user_id": "",
            "retweeted_status_id": "543634738620026880",
            "retweeted_status_timestamp": "2014-12-13 05:13:16 +0000",
            "retweeted_status_user_id": "15835434",
            "source": "<a href=\"http://twitter.com/download/iphone\" rel=\"nofollow\">Twitter for iPhone</a>",
            "text": "RT @moznion: \u30db\u30ef\u30a4\u30c8\u30a2\u30eb\u30d0\u30e0\uff0c\u51ac\u306e\u5b63\u8a9e\u3063\u307d\u3044\u3051\u30698\u6587\u5b57\u3060\u304b\u3089\u53e5\u306b\u7d44\u307f\u8fbc\u3081\u306a\u3044",
            "timestamp": "2014-12-13 05:20:24 +0000",
            "tweet_id": "543636534922969088"
        },
        {
            "expanded_urls": "",
            "in_reply_to_status_id": "",
            "in_reply_to_user_id": "",
            "retweeted_status_id": "",
            "retweeted_status_timestamp": "",
            "retweeted_status_user_id": "",
            "source": "<a href=\"http://twitter.com/download/iphone\" rel=\"nofollow\">Twitter for iPhone</a>",
            "text": "\u30db\u30ef\u30eb\u30d0",
            "timestamp": "2014-12-13 05:20:30 +0000",
            "tweet_id": "543636558708879360"
        },
        {
            "expanded_urls": "",
            "in_reply_to_status_id": "",
            "in_reply_to_user_id": "",
            "retweeted_status_id": "",
            "retweeted_status_timestamp": "",
            "retweeted_status_user_id": "",
            "source": "<a href=\"http://twitter.com/#!/download/ipad\" rel=\"nofollow\">Twitter for iPad</a>",
            "text": "Amazon\u306e\u307b\u3057\u3044\u7269\u30ea\u30b9\u30c8\u304c\u30d7\u30eb\u30c0\u30a6\u30f3\u30e1\u30cb\u30e5\u30fc\u306b\u306a\u3063\u3066\u3044\u3066\u62bc\u3057\u3066\u3059\u3050\u79fb\u52d5\u3067\u304d\u306a\u3044\u306e\u3084\u3081\u3066\u307b\u3057\u3044",
            "timestamp": "2014-12-13 06:09:31 +0000",
            "tweet_id": "543648894874161152"
        },
        {
            "expanded_urls": "https://twitter.com/gaiko_kujin/status/542645471479492608/photo/1,https://twitter.com/gaiko_kujin/status/542645471479492608/photo/1",
            "in_reply_to_status_id": "",
            "in_reply_to_user_id": "",
            "retweeted_status_id": "542645471479492608",
            "retweeted_status_timestamp": "2014-12-10 11:42:16 +0000",
            "retweeted_status_user_id": "93005530",
            "source": "<a href=\"http://twitter.com/#!/download/ipad\" rel=\"nofollow\">Twitter for iPad</a>",
            "text": "RT @gaiko_kujin: \u30bf\u30d0\u30b3\u3068\u30d9\u30f3\u30c4\uff14\u30b3\u30de http://t.co/jsYCuqkjed",
            "timestamp": "2014-12-13 06:19:37 +0000",
            "tweet_id": "543651436228145152"
        },
        {
            "expanded_urls": "",
            "in_reply_to_status_id": "",
            "in_reply_to_user_id": "",
            "retweeted_status_id": "543655176561623040",
            "retweeted_status_timestamp": "2014-12-13 06:34:29 +0000",
            "retweeted_status_user_id": "13902442",
            "source": "<a href=\"http://twitter.com/#!/download/ipad\" rel=\"nofollow\">Twitter for iPad</a>",
            "text": "RT @asaokitan: \u3093\u3001\u30db\u30ef\u30a4\u30c8\u30a2\u30eb\u30d0\u30e0\u306f\u53e5\u306b\u306a\u308b\u306e\u3067\u306f\uff1f",
            "timestamp": "2014-12-13 06:37:26 +0000",
            "tweet_id": "543655918156513281"
        },
        {
            "expanded_urls": "",
            "in_reply_to_status_id": "",
            "in_reply_to_user_id": "",
            "retweeted_status_id": "",
            "retweeted_status_timestamp": "",
            "retweeted_status_user_id": "",
            "source": "<a href=\"http://twitter.com/#!/download/ipad\" rel=\"nofollow\">Twitter for iPad</a>",
            "text": "\u4e00\u77ac\u308f\u304b\u3089\u306a\u304b\u3063\u305f",
            "timestamp": "2014-12-13 06:37:36 +0000",
            "tweet_id": "543655962872000512"
        },
        {
            "expanded_urls": "",
            "in_reply_to_status_id": "",
            "in_reply_to_user_id": "",
            "retweeted_status_id": "",
            "retweeted_status_timestamp": "",
            "retweeted_status_user_id": "",
            "source": "<a href=\"http://twitter.com/#!/download/ipad\" rel=\"nofollow\">Twitter for iPad</a>",
            "text": "\u30a6\u30a3\u30ea\u30a2\u30e0\u30bd\u30f3 \u30de\u30af\u30ed\u7d4c\u6e08\u5b66\u30081\u3009Amazon \u3067\u4e2d\u53e4\u8cfc\u5165\u3002",
            "timestamp": "2014-12-13 06:45:42 +0000",
            "tweet_id": "543657998149636096"
        },
        {
            "expanded_urls": "",
            "in_reply_to_status_id": "",
            "in_reply_to_user_id": "",
            "retweeted_status_id": "",
            "retweeted_status_timestamp": "",
            "retweeted_status_user_id": "",
            "source": "<a href=\"http://twitter.com/#!/download/ipad\" rel=\"nofollow\">Twitter for iPad</a>",
            "text": "\u8d85\u30e4\u30d0\u3044\u7d4c\u6e08\u5b66 Amazon \u3067\u4e2d\u53e4\u8cfc\u5165\u3002",
            "timestamp": "2014-12-13 06:50:54 +0000",
            "tweet_id": "543659306424352769"
        },
        {
            "expanded_urls": "",
            "in_reply_to_status_id": "",
            "in_reply_to_user_id": "",
            "retweeted_status_id": "",
            "retweeted_status_timestamp": "",
            "retweeted_status_user_id": "",
            "source": "<a href=\"http://twitter.com/#!/download/ipad\" rel=\"nofollow\">Twitter for iPad</a>",
            "text": "\u305d\u306e\u79d1\u5b66\u304c\u6210\u529f\u3092\u6c7a\u3081\u308b Amazon\u3067\u4e2d\u53e4\u8cfc\u5165\u3002",
            "timestamp": "2014-12-13 07:18:11 +0000",
            "tweet_id": "543666173762498561"
        },
        {
            "expanded_urls": "",
            "in_reply_to_status_id": "",
            "in_reply_to_user_id": "",
            "retweeted_status_id": "",
            "retweeted_status_timestamp": "",
            "retweeted_status_user_id": "",
            "source": "<a href=\"http://twitter.com/#!/download/ipad\" rel=\"nofollow\">Twitter for iPad</a>",
            "text": "\u65e5\u672c\u4eba\u3082\u60a9\u3080\u65e5\u672c\u8a9e \u3053\u3068\u3070\u306e\u8aa4\u7528\u306f\u306a\u305c\u751f\u307e\u308c\u308b\u306e\u304b? \u300c\u7684\u3092\u5f97\u308b\u300d\u306b\u3064\u3044\u3066\u306e\u8a18\u8ff0\u304c\u3042\u307e\u308a\u306b\u3082\u9069\u5f53\u3067\u307b\u3057\u3044\u7269\u30ea\u30b9\u30c8\u304b\u3089\u5916\u3057\u305f\u3002\uff08\u3053\u3046\u3044\u3046\u3053\u3068\u304c\u3042\u308b\u304b\u3089\u5e97\u982d\u3067\u898b\u306a\u3044\u3068\u8cb7\u3048\u306a\u3044\uff09\uff08\u3044\u3084\u3001\u9593\u9055\u3063\u305f\u672c\u3092\u8cb7\u3046\u30b3\u30b9\u30c8\u306f\u5e97\u982d\u307e\u3067\u884c\u304f\u30b3\u30b9\u30c8\u3088\u308a\u306f\u308b\u304b\u306b\u5c0f\u3055\u3044\uff09\uff08\u5e97\u306b\u884c\u304f\u52b9\u7528\u306f\uff09\uff08\u304d\u308a\u304c\u306a\u3044\uff09",
            "timestamp": "2014-12-13 07:29:11 +0000",
            "tweet_id": "543668940715458561"
        },
        {
            "expanded_urls": "",
            "in_reply_to_status_id": "",
            "in_reply_to_user_id": "",
            "retweeted_status_id": "",
            "retweeted_status_timestamp": "",
            "retweeted_status_user_id": "",
            "source": "<a href=\"http://twitter.com/#!/download/ipad\" rel=\"nofollow\">Twitter for iPad</a>",
            "text": "\u307c\u304f\u306f\u9593\u9055\u3063\u305f\u9078\u629e\u3092\u3059\u308b\u3053\u3068\u306b\u3088\u308b\u7cbe\u795e\u7684\u30c0\u30e1\u30fc\u30b8\u304c\u5927\u304d\u3044\u3068\u3044\u3046\u5fc3\u306e\u7279\u5fb4\u3092\u6301\u3063\u3066\u3044\u308b\u306e\u3067\u4e00\u898b\u975e\u5408\u7406\u306a\u884c\u52d5\u3092\u53d6\u308b\u3051\u308c\u3069\u3001\u305d\u308c\u306f\u5fc3\u306e\u7279\u6027\u3092\u8003\u3048\u305f\u3046\u3048\u3067\u306e\u5408\u7406\u7684\u306a\u884c\u52d5\u306a\u306e\u3060\uff08\u5fc3\u306e\u7279\u6027\u3092\u5909\u3048\u308b\u53ef\u80fd\u6027\u3068\u3044\u3063\u305f\u4e0d\u78ba\u5b9a\u306a\u3053\u3068\u3092\u8a08\u7b97\u306b\u5165\u308c\u308b\u3068\u4eca\u5f8c\u306e\u4eba\u751f\u306e\u9577\u3055\u306e\u3088\u3046\u306a\u5909\u6570\u304c\u7d61\u3093\u3067\u304d\u3066\u624b\u306b\u8ca0\u3048\u306a\u3044\uff09",
            "timestamp": "2014-12-13 07:32:43 +0000",
            "tweet_id": "543669830469967872"
        },
        {
            "expanded_urls": "",
            "in_reply_to_status_id": "",
            "in_reply_to_user_id": "",
            "retweeted_status_id": "",
            "retweeted_status_timestamp": "",
            "retweeted_status_user_id": "",
            "source": "<a href=\"http://twitter.com/#!/download/ipad\" rel=\"nofollow\">Twitter for iPad</a>",
            "text": "\u30b3\u30ec\u30e2\u65e5\u672c\u8a9e\u30a2\u30eb\u30ab\uff1f \u4e00\u77ac\u3067\u8cb7\u3046\u3079\u304d\u672c\u3060\u3068\u308f\u304b\u308b",
            "timestamp": "2014-12-13 07:34:03 +0000",
            "tweet_id": "543670167666835456"
        },
        {
            "expanded_urls": "",
            "in_reply_to_status_id": "",
            "in_reply_to_user_id": "",
            "retweeted_status_id": "",
            "retweeted_status_timestamp": "",
            "retweeted_status_user_id": "",
            "source": "<a href=\"http://twitter.com/#!/download/ipad\" rel=\"nofollow\">Twitter for iPad</a>",
            "text": "\u30b3\u30ec\u30e2\u65e5\u672c\u8a9e\u30a2\u30eb\u30ab\uff1f \u7570\u4eba\u306e\u3053\u3068\u3070\u304c\u751f\u307e\u308c\u308b\u3068\u304d honto \u3067\u65b0\u54c1\u8cfc\u5165\u3002\uff0810%\u5f15\u304d\u30af\u30fc\u30dd\u30f3\u304c\u3042\u3063\u305f\u306e\u3067\uff09",
            "timestamp": "2014-12-13 07:37:25 +0000",
            "tweet_id": "543671013326598144"
        },
        {
            "expanded_urls": "",
            "in_reply_to_status_id": "",
            "in_reply_to_user_id": "",
            "retweeted_status_id": "",
            "retweeted_status_timestamp": "",
            "retweeted_status_user_id": "",
            "source": "<a href=\"http://twitter.com/#!/download/ipad\" rel=\"nofollow\">Twitter for iPad</a>",
            "text": "\u4e00\u77ac\u3067\u8cb7\u3046\u3079\u304d\u672c\u3060\u3068\u308f\u304b\u3063\u305f\u306e\u3067\u4e00\u77ac\u3067\u8cb7\u3063\u305f\uff08\u4fc2\u308a\u5148\u304c\u9055\u3046\uff09",
            "timestamp": "2014-12-13 07:37:58 +0000",
            "tweet_id": "543671155249250304"
        },
        {
            "expanded_urls": "",
            "in_reply_to_status_id": "",
            "in_reply_to_user_id": "",
            "retweeted_status_id": "543650603449065472",
            "retweeted_status_timestamp": "2014-12-13 06:16:19 +0000",
            "retweeted_status_user_id": "158928552",
            "source": "<a href=\"http://twitter.com/#!/download/ipad\" rel=\"nofollow\">Twitter for iPad</a>",
            "text": "RT @toppinpararin: 5\u6b73\u5a18\u306b\u300c\u304a\u304b\u3042\u3055\u3093\u306e\u3057\u3087\u3046\u3089\u3044\u306e\u3086\u3081\u306f\u306a\u306b\uff1f\u300d\u3068\u805e\u304b\u308c\u8fd4\u4e8b\u306b\u7aae\u3057\u3066\u3044\u308b\u3068\u3001\u614c\u3066\u3066\u5a18\u304c\u300c\u3042\u3063\u307e\u3061\u304c\u3048\u305f\uff01\u305d\u3046\u3060\u3088\u306d\u3001\u304a\u304b\u3042\u3055\u3093\u306e\u3057\u3087\u3046\u3089\u3044\u3001\u3082\u3046\u304a\u308f\u3063\u3066\u308b\u3082\u3093\u306d\uff01\u3054\u3081\u3093\u3054\u3081\u3093\u300d\u3068\u6c17\u3092\u9063\u308f\u308c\u305f\u3002",
            "timestamp": "2014-12-13 08:41:39 +0000",
            "tweet_id": "543687180518830080"
        },
        {
            "expanded_urls": "",
            "in_reply_to_status_id": "",
            "in_reply_to_user_id": "",
            "retweeted_status_id": "",
            "retweeted_status_timestamp": "",
            "retweeted_status_user_id": "",
            "source": "<a href=\"http://twitter.com/#!/download/ipad\" rel=\"nofollow\">Twitter for iPad</a>",
            "text": "\u8eca\u3067\u30d7\u30fc\u30eb\u3078\u3002",
            "timestamp": "2014-12-13 08:43:36 +0000",
            "tweet_id": "543687672087056384"
        },
        {
            "expanded_urls": "",
            "in_reply_to_status_id": "",
            "in_reply_to_user_id": "",
            "retweeted_status_id": "",
            "retweeted_status_timestamp": "",
            "retweeted_status_user_id": "",
            "source": "<a href=\"http://twitter.com/#!/download/ipad\" rel=\"nofollow\">Twitter for iPad</a>",
            "text": "\u300c\u3093\u3001\u300d\u306f\u8133\u5185\u4e8c\u30e2\u30fc\u30e9\u306b\u306a\u308b\u306e\u3067\u6c17\u3065\u304f\u306e\u304c\u9045\u308c\u305f\uff08\u3060\u3044\u3076\u524d\u306e\u8a71\u984c\uff09",
            "timestamp": "2014-12-13 09:02:12 +0000",
            "tweet_id": "543692349805584385"
        },
        {
            "expanded_urls": "",
            "in_reply_to_status_id": "",
            "in_reply_to_user_id": "",
            "retweeted_status_id": "",
            "retweeted_status_timestamp": "",
            "retweeted_status_user_id": "",
            "source": "<a href=\"http://twitter.com/#!/download/ipad\" rel=\"nofollow\">Twitter for iPad</a>",
            "text": "\u30ab\u30ec\u30fc\u3092\u98df\u3079\u305f\u3002",
            "timestamp": "2014-12-13 10:31:35 +0000",
            "tweet_id": "543714844654850048"
        },
        {
            "expanded_urls": "https://twitter.com/cue_449ds/status/543684073864978432",
            "in_reply_to_status_id": "",
            "in_reply_to_user_id": "",
            "retweeted_status_id": "",
            "retweeted_status_timestamp": "",
            "retweeted_status_user_id": "",
            "source": "<a href=\"http://twitter.com/#!/download/ipad\" rel=\"nofollow\">Twitter for iPad</a>",
            "text": "\u3053\u308c\u8aad\u3093\u3067\u304b\u306a\u308a\u6df7\u4e71\u3057\u305f\u3093\u3060\u3051\u3069\u3001\u30a2\u30af\u30a2\u3068\u3044\u3046\u306e\u306f\u30d7\u30ea\u30a6\u30b9\u3058\u3083\u306a\u3044\u3051\u3069\u30d7\u30ea\u30a6\u30b9\u306e\u4ef2\u9593\u6271\u3044\u306a\u306e\u304b https://t.co/QzHZ6u9ZtM",
            "timestamp": "2014-12-13 10:43:19 +0000",
            "tweet_id": "543717798921248768"
        },
        {
            "expanded_urls": "",
            "in_reply_to_status_id": "",
            "in_reply_to_user_id": "",
            "retweeted_status_id": "543707342231961600",
            "retweeted_status_timestamp": "2014-12-13 10:01:46 +0000",
            "retweeted_status_user_id": "5310852",
            "source": "<a href=\"http://twitter.com/#!/download/ipad\" rel=\"nofollow\">Twitter for iPad</a>",
            "text": "RT @tanakh: \uff82\uff72\uff6f\uff80\uff67\uff70\u3063\u3066\u3044\u3046SNS\uff08\uff1f\uff09\u306f\u305d\u3082\u305d\u3082\uff8b\uff6e\uff9b\uff70\u95a2\u4fc2\u304c\u4ed6\u306e\u591a\u304f\u306eSNS\u3068\u306f\u9055\u3063\u3066\u3001\u6709\u5411\u30b0\u30e9\u30d5\u306a\u306e\u304c\u3001\u6700\u5927\u306e\u7279\u5fb4\u306a\u306e\u304b\u3082\u3057\u308c\u306a\u3044\u304b\u3089\u306a\u3042\u3063\u30fb\u30fb\u30fb",
            "timestamp": "2014-12-13 10:45:24 +0000",
            "tweet_id": "543718322294898689"
        },
        {
            "expanded_urls": "",
            "in_reply_to_status_id": "",
            "in_reply_to_user_id": "",
            "retweeted_status_id": "",
            "retweeted_status_timestamp": "",
            "retweeted_status_user_id": "",
            "source": "<a href=\"http://twitter.com/#!/download/ipad\" rel=\"nofollow\">Twitter for iPad</a>",
            "text": "Google+",
            "timestamp": "2014-12-13 10:45:38 +0000",
            "tweet_id": "543718379513593856"
        },
        {
            "expanded_urls": "https://twitter.com/_hanyu/status/543282868806356992/photo/1,https://twitter.com/_hanyu/status/543282868806356992/photo/1",
            "in_reply_to_status_id": "",
            "in_reply_to_user_id": "",
            "retweeted_status_id": "543282868806356992",
            "retweeted_status_timestamp": "2014-12-12 05:55:04 +0000",
            "retweeted_status_user_id": "451032210",
            "source": "<a href=\"http://twitter.com/#!/download/ipad\" rel=\"nofollow\">Twitter for iPad</a>",
            "text": "RT @_hanyu: \ubbf8\uad6d\uc758 \ud754\ud55c \ubc29\uc1a1\uc0ac\uace0...\uc778\ub370 \uadc0\uc5fd\ub2e4\u314b\u314b\u314b\u314b\u314b\u314b\u314b\u314b\u314b\u314b\u314b\u314b http://t.co/Rx9eO2sN37",
            "timestamp": "2014-12-13 10:58:42 +0000",
            "tweet_id": "543721669164941312"
        },
        {
            "expanded_urls": "",
            "in_reply_to_status_id": "543727547368742913",
            "in_reply_to_user_id": "13902442",
            "retweeted_status_id": "",
            "retweeted_status_timestamp": "",
            "retweeted_status_user_id": "",
            "source": "<a href=\"http://twitter.com/#!/download/ipad\" rel=\"nofollow\">Twitter for iPad</a>",
            "text": "@asaokitan \u8eca\u306e\u3053\u3068\u304c\u308f\u304b\u308b\u4eba\u306b\u3068\u3063\u3066\u306f\u30a2\u30af\u30a2\u306f\u975e\u5178\u578b\u7684\u30d7\u30ea\u30a6\u30b9\u3068\u3044\u3063\u305f\u611f\u3058\u306e\u3088\u3046\u3067\u3059\u306d\u3002\u5de6\u306e\u30a2\u30af\u30a2\u304c\u307e\u305f\u6df7\u4e71\u3092\u8a98\u3046\u3002",
            "timestamp": "2014-12-13 11:23:16 +0000",
            "tweet_id": "543727849727741955"
        },
        {
            "expanded_urls": "",
            "in_reply_to_status_id": "543728807257964548",
            "in_reply_to_user_id": "13902442",
            "retweeted_status_id": "",
            "retweeted_status_timestamp": "",
            "retweeted_status_user_id": "",
            "source": "<a href=\"http://itunes.apple.com/us/app/twitter/id409789998?mt=12\" rel=\"nofollow\">Twitter for Mac</a>",
            "text": "@asaokitan \u3084\u3063\u3071\u308a\u305d\u3053\u3067\u3059\u3088\u306d\u3047\u3002\u30a2\u30af\u30a2\u2252\u30d7\u30ea\u30a6\u30b9\u3068\u3044\u3046\u4eee\u8aac\u306b\u305f\u3069\u308a\u7740\u304f\u307e\u3067\u6642\u9593\u304c\u304b\u304b\u308a\u307e\u3057\u305f\u3002",
            "timestamp": "2014-12-13 11:27:59 +0000",
            "tweet_id": "543729040767459328"
        },
        {
            "expanded_urls": "",
            "in_reply_to_status_id": "543730949213528064",
            "in_reply_to_user_id": "1106162760",
            "retweeted_status_id": "",
            "retweeted_status_timestamp": "",
            "retweeted_status_user_id": "",
            "source": "<a href=\"http://itunes.apple.com/us/app/twitter/id409789998?mt=12\" rel=\"nofollow\">Twitter for Mac</a>",
            "text": "@metalinguistic @asaokitan \u306f\u3044\u3001\u305d\u3053\u306b\u305f\u3069\u308a\u7740\u304f\u306e\u306b\u304b\u306a\u308a\u82e6\u52b4\u3057\u305f\u3068\u3044\u3046\u3053\u3068\u3067\u3057\u305f\u3002",
            "timestamp": "2014-12-13 11:36:12 +0000",
            "tweet_id": "543731105472335873"
        },
        {
            "expanded_urls": "",
            "in_reply_to_status_id": "",
            "in_reply_to_user_id": "",
            "retweeted_status_id": "",
            "retweeted_status_timestamp": "",
            "retweeted_status_user_id": "",
            "source": "<a href=\"http://itunes.apple.com/us/app/twitter/id409789998?mt=12\" rel=\"nofollow\">Twitter for Mac</a>",
            "text": "\u4e01\u534a\u535a\u6253\u306e\u3084\u3064\u304b",
            "timestamp": "2014-12-13 11:38:04 +0000",
            "tweet_id": "543731577222463489"
        },
        {
            "expanded_urls": "https://twitter.com/livein_china/status/543685086072143873/photo/1,https://twitter.com/livein_china/status/543685086072143873/photo/1",
            "in_reply_to_status_id": "",
            "in_reply_to_user_id": "",
            "retweeted_status_id": "543685086072143873",
            "retweeted_status_timestamp": "2014-12-13 08:33:20 +0000",
            "retweeted_status_user_id": "60238858",
            "source": "<a href=\"http://itunes.apple.com/us/app/twitter/id409789998?mt=12\" rel=\"nofollow\">Twitter for Mac</a>",
            "text": "RT @livein_china: \u3042\u307e\u304a\u3046 \u304b\u3068\u601d\u3063\u305f\u3089\u9055\u3046\u54c1\u7a2e\u3089\u3057\u3044 http://t.co/YEPYvCRdKa",
            "timestamp": "2014-12-13 11:42:08 +0000",
            "tweet_id": "543732598288052227"
        },
        {
            "expanded_urls": "http://econ.st/1zzQ0iY,https://twitter.com/TheEconomist/status/543723518358474752/photo/1,http://econ.st/1zzQ0iY,https://twitter.com/TheEconomist/status/543723518358474752/photo/1",
            "in_reply_to_status_id": "",
            "in_reply_to_user_id": "",
            "retweeted_status_id": "543723518358474752",
            "retweeted_status_timestamp": "2014-12-13 11:06:03 +0000",
            "retweeted_status_user_id": "5988062",
            "source": "<a href=\"http://itunes.apple.com/us/app/twitter/id409789998?mt=12\" rel=\"nofollow\">Twitter for Mac</a>",
            "text": "RT @TheEconomist: A new paper shows that reducing working hours can be good for productivity  http://t.co/wFGAm7nb0G http://t.co/eT5GH6XxOT",
            "timestamp": "2014-12-13 11:48:51 +0000",
            "tweet_id": "543734289892798466"
        },
        {
            "expanded_urls": "",
            "in_reply_to_status_id": "",
            "in_reply_to_user_id": "",
            "retweeted_status_id": "543725136109502465",
            "retweeted_status_timestamp": "2014-12-13 11:12:29 +0000",
            "retweeted_status_user_id": "17364190",
            "source": "<a href=\"http://itunes.apple.com/us/app/twitter/id409789998?mt=12\" rel=\"nofollow\">Twitter for Mac</a>",
            "text": "RT @Cernobyl: \u6751\u4e00\u756a\u306e\u5bb6\u96fb\u91cf\u8ca9\u5e97\u306b\u884c\u3063\u3066\u300c Chromebook \u3042\u308a\u307e\u3059\u304b\uff1f\u300d\u3063\u3066\u805e\u3044\u305f\u3089\u300c\u4f55\u8a00\u3063\u3066\u3093\u3060\u3053\u3044\u3064\u300d\u307f\u305f\u3044\u306a\u9854\u3055\u308c\u305f\u306e\u3067\u6ce3\u304d\u306a\u304c\u3089\u5e30\u3063\u3066\u304d\u305f",
            "timestamp": "2014-12-13 11:49:59 +0000",
            "tweet_id": "543734574887358464"
        },
        {
            "expanded_urls": "http://htn.to/sJDUB4",
            "in_reply_to_status_id": "",
            "in_reply_to_user_id": "",
            "retweeted_status_id": "543725977482715136",
            "retweeted_status_timestamp": "2014-12-13 11:15:49 +0000",
            "retweeted_status_user_id": "3783901",
            "source": "<a href=\"http://itunes.apple.com/us/app/twitter/id409789998?mt=12\" rel=\"nofollow\">Twitter for Mac</a>",
            "text": "RT @masanork: \u540c\u611f\u2192\u300c\u4ee3\u8868\u306a\u304f\u3057\u3066\u8ab2\u7a0e\u306a\u3057\u300d\u3068\u3044\u3046\u30b9\u30ed\u30fc\u30ac\u30f3\u306f\u3001\u300c\u5897\u7a0e\u5148\u9001\u308a\u3067\u653f\u5e9c\u50b5\u52d9\u3092\u62e1\u5927\u3057\u3001\u5c06\u6765\u306b\u8ca0\u62c5\u5897\u3092\u5148\u9001\u308a\u3059\u308b\u306a\u3089\u3070\u3001\u5c06\u6765\u306e\u7d0d\u7a0e\u8005\u306e\u4ee3\u8868\u3092\u56fd\u4f1a\u306b\u51fa\u305b\uff01\u300d\u304c\u6b63\u3057\u3044\u89e3\u91c8 / \u201c\u300c\u516c\u50b5\u306e\u4e2d\u7acb\u547d\u984c\u300d\u3068\u300c\u4ee3\u8868\u306a\u304f\u3057\u3066\u8ab2\u7a0e\u306a\u3057\u300d : \u30a2\u30b4\u30e9 - \u2026\u201d http://\u2026",
            "timestamp": "2014-12-13 11:58:25 +0000",
            "tweet_id": "543736699579166720"
        },
        {
            "expanded_urls": "https://twitter.com/cocomoff/status/543727706941046785/photo/1,https://twitter.com/cocomoff/status/543727706941046785/photo/1",
            "in_reply_to_status_id": "",
            "in_reply_to_user_id": "",
            "retweeted_status_id": "543727706941046785",
            "retweeted_status_timestamp": "2014-12-13 11:22:41 +0000",
            "retweeted_status_user_id": "154428317",
            "source": "<a href=\"http://itunes.apple.com/us/app/twitter/id409789998?mt=12\" rel=\"nofollow\">Twitter for Mac</a>",
            "text": "RT @cocomoff: \u9069\u5f53\u306b\u8cb7\u3063\u305f\u3082\u306e\u306a\u3093\u3060\u3051\u3069\u30af\u30c3\u30bd\u5f79\u306b\u7acb\u3064\u3053\u308c http://t.co/uQBfs2U1xF",
            "timestamp": "2014-12-13 11:59:42 +0000",
            "tweet_id": "543737020816695297"
        },
        {
            "expanded_urls": "",
            "in_reply_to_status_id": "",
            "in_reply_to_user_id": "",
            "retweeted_status_id": "542615447510581249",
            "retweeted_status_timestamp": "2014-12-10 09:42:58 +0000",
            "retweeted_status_user_id": "9747262",
            "source": "<a href=\"http://itunes.apple.com/us/app/twitter/id409789998?mt=12\" rel=\"nofollow\">Twitter for Mac</a>",
            "text": "RT @repon: \u6628\u65e5\u9a5a\u3044\u305f\u306e\u306f\u3001\u300c\u934b\u3092\u3064\u3064\u304f\u300d\u3068\u3044\u3046\u6240\u4f5c\u304c\u3001\u9ad8\u5ea6\u6210\u9577\u671f\u306b\u306a\u3063\u3066\u300c\u30a4\u30ef\u30bf\u30cb\u306e\u30ab\u30bb\u30c3\u30c8\u30b3\u30f3\u30ed\u300d\u306b\u3088\u3063\u3066\u4f5c\u3089\u308c\u305f\u3001\u3068\u3044\u3046\u3053\u3068\u3002\u305d\u308c\u307e\u3067\u306f\u65e5\u672c\u3082\u3001\u305d\u308c\u305e\u308c\u306e\u98df\u5668\u306b\u76db\u308a\u3064\u3051\u308b\u304b\u53d6\u308a\u5206\u3051\u3066\u304b\u3089\u98df\u3079\u308b\u306e\u307f\u3067\u3001\u540c\u3058\u98df\u6750\u3092\u8907\u6570\u4eba\u3067\u7bb8\u3067\u3064\u3064\u304f\u3001\u3068\u3044\u3046\u6587\u5316\u306f\u7121\u304b\u3063\u305f\u3089\u3057\u3044\u3002",
            "timestamp": "2014-12-13 12:03:01 +0000",
            "tweet_id": "543737856489836544"
        },
        {
            "expanded_urls": "",
            "in_reply_to_status_id": "",
            "in_reply_to_user_id": "",
            "retweeted_status_id": "",
            "retweeted_status_timestamp": "",
            "retweeted_status_user_id": "",
            "source": "<a href=\"http://itunes.apple.com/us/app/twitter/id409789998?mt=12\" rel=\"nofollow\">Twitter for Mac</a>",
            "text": "\u305d\u308c\u307e\u3067\u306f\u30ac\u30b9\u30db\u30fc\u30b9\u3092\u3064\u306a\u3044\u3067\u3044\u305f\u306e\u304b",
            "timestamp": "2014-12-13 12:03:29 +0000",
            "tweet_id": "543737972265209858"
        },
        {
            "expanded_urls": "",
            "in_reply_to_status_id": "543738567118163969",
            "in_reply_to_user_id": "14923940",
            "retweeted_status_id": "",
            "retweeted_status_timestamp": "",
            "retweeted_status_user_id": "",
            "source": "<a href=\"http://itunes.apple.com/us/app/twitter/id409789998?mt=12\" rel=\"nofollow\">Twitter for Mac</a>",
            "text": "@kani7 \u3044\u308d\u308a\u2192\u30ac\u30b9\u30db\u30fc\u30b9\u2192\u30ab\u30bb\u30c3\u30c8\u30b3\u30f3\u30ed \u3068\u3044\u3046\u611f\u3058\u3067\u3057\u3087\u3046\u304b\u306d\u3002",
            "timestamp": "2014-12-13 12:06:19 +0000",
            "tweet_id": "543738685527564289"
        },
        {
            "expanded_urls": "",
            "in_reply_to_status_id": "543739299431071744",
            "in_reply_to_user_id": "14923940",
            "retweeted_status_id": "",
            "retweeted_status_timestamp": "",
            "retweeted_status_user_id": "",
            "source": "<a href=\"http://itunes.apple.com/us/app/twitter/id409789998?mt=12\" rel=\"nofollow\">Twitter for Mac</a>",
            "text": "@kani7 \u304a\u3049\u3001\u306a\u308b\u307b\u3069\u3002\u5c0f\u578b\u306e\u30ac\u30b9\u30dc\u30f3\u30d9\u3068\u3044\u3046\u306e\u304c\u3042\u3063\u305f\u3093\u3067\u3059\u306d\u3002",
            "timestamp": "2014-12-13 12:09:40 +0000",
            "tweet_id": "543739527991291905"
        },
        {
            "expanded_urls": "",
            "in_reply_to_status_id": "",
            "in_reply_to_user_id": "",
            "retweeted_status_id": "",
            "retweeted_status_timestamp": "",
            "retweeted_status_user_id": "",
            "source": "<a href=\"http://itunes.apple.com/us/app/twitter/id409789998?mt=12\" rel=\"nofollow\">Twitter for Mac</a>",
            "text": "SICP \u3092\u3084\u308b\u3002",
            "timestamp": "2014-12-13 12:11:03 +0000",
            "tweet_id": "543739874939899906"
        },
        {
            "expanded_urls": "",
            "in_reply_to_status_id": "543741610610020353",
            "in_reply_to_user_id": "14923940",
            "retweeted_status_id": "",
            "retweeted_status_timestamp": "",
            "retweeted_status_user_id": "",
            "source": "<a href=\"http://itunes.apple.com/us/app/twitter/id409789998?mt=12\" rel=\"nofollow\">Twitter for Mac</a>",
            "text": "@kani7 \u306a\u308b\u307b\u3069\u3002\u305d\u308c\u306f\u91cd\u3044\u3067\u3059\u306d\u3002",
            "timestamp": "2014-12-13 12:18:16 +0000",
            "tweet_id": "543741694844227584"
        },
        {
            "expanded_urls": "",
            "in_reply_to_status_id": "",
            "in_reply_to_user_id": "",
            "retweeted_status_id": "543738738942017536",
            "retweeted_status_timestamp": "2014-12-13 12:06:32 +0000",
            "retweeted_status_user_id": "14087520",
            "source": "<a href=\"http://twitter.com/#!/download/ipad\" rel=\"nofollow\">Twitter for iPad</a>",
            "text": "RT @necocen: \u300c\u3054\u9759\u8074\u3042\u308a\u304c\u3068\u3046\u3054\u3056\u3044\u307e\u3057\u305f\u300d\u30b9\u30e9\u30a4\u30c9\u6279\u5224\u3092\u7e70\u308a\u8fd4\u3057\u76ee\u306b\u3057\u305f\u305f\u3081\u306b\u300c\u3054\u9759\u8074\u3042\u308a\u304c\u3068\u3046\u3054\u3056\u3044\u307e\u3057\u305f\u300d\u30b9\u30e9\u30a4\u30c9\u3092\u898b\u308b\u305f\u3073\u306b\u300c\u3042\u3063\u3053\u306e\u4eba\u306f\u300e\u3054\u9759\u8074\u3042\u308a\u304c\u3068\u3046\u3054\u3056\u3044\u307e\u3057\u305f\u300f\u30b9\u30e9\u30a4\u30c9\u3092\u4f5c\u308b\u4eba\u306a\u3093\u3060\u300d\u3063\u3066\u601d\u3063\u3066\u3057\u307e\u3046\u306e\u300c\u3054\u6e05\u8074\u3042\u308a\u304c\u3068\u3046\u3054\u3056\u3044\u307e\u3057\u305f\u300d\u30b9\u30e9\u30a4\u30c9\u53cd\u5bfe\u2026",
            "timestamp": "2014-12-13 12:54:17 +0000",
            "tweet_id": "543750758651285505"
        },
        {
            "expanded_urls": "",
            "in_reply_to_status_id": "",
            "in_reply_to_user_id": "",
            "retweeted_status_id": "",
            "retweeted_status_timestamp": "",
            "retweeted_status_user_id": "",
            "source": "<a href=\"http://itunes.apple.com/us/app/twitter/id409789998?mt=12\" rel=\"nofollow\">Twitter for Mac</a>",
            "text": "10\u6642\u304b\u3089\u306f\u30b9\u30da\u30a4\u30f3\u8a9e\u306eSkype\u30ec\u30c3\u30b9\u30f3\u3002",
            "timestamp": "2014-12-13 12:59:39 +0000",
            "tweet_id": "543752106025308160"
        },
        {
            "expanded_urls": "",
            "in_reply_to_status_id": "",
            "in_reply_to_user_id": "",
            "retweeted_status_id": "",
            "retweeted_status_timestamp": "",
            "retweeted_status_user_id": "",
            "source": "<a href=\"http://itunes.apple.com/us/app/twitter/id409789998?mt=12\" rel=\"nofollow\">Twitter for Mac</a>",
            "text": "\u30b9\u30da\u30a4\u30f3\u8a9e\u30ec\u30c3\u30b9\u30f3\u7d42\u308f\u308a\u3002",
            "timestamp": "2014-12-13 14:01:45 +0000",
            "tweet_id": "543767735360950272"
        },
        {
            "expanded_urls": "",
            "in_reply_to_status_id": "",
            "in_reply_to_user_id": "",
            "retweeted_status_id": "543764546565844992",
            "retweeted_status_timestamp": "2014-12-13 13:49:05 +0000",
            "retweeted_status_user_id": "350789410",
            "source": "<a href=\"http://twitter.com/#!/download/ipad\" rel=\"nofollow\">Twitter for iPad</a>",
            "text": "RT @hiroshnakagawa3: @unnonouno \u306f\u3044\u3002\u3088\u3046\u3059\u308b\u306b\u304a\u91d1\u306e\u4fa1\u5024\u304c\u6e1b\u308a\u307e\u3059\u304b\u3089\u3001\u7b49\u4fa1\u7684\u306b\u8ca0\u50b5\u304c\u6e1b\u308a\u307e\u3059\u304c\u3001\u305d\u306e\u30c4\u30b1\u306f\u56fd\u6c11\u306e\u84c4\u8ca1\u3084\u53ef\u51e6\u5206\u6240\u5f97\u306b\u5b9f\u8cea\u6e1b\u306b\u306a\u3063\u3066\u8df3\u306d\u8fd4\u308b\u3068\u3044\u3046\u56f3\u5f0f\u3060\u3068\u601d\u3044\u307e\u3059\u3002\u73fe\u72b6\u306e\u65e5\u9280\u306e\u653f\u7b56\u3067\u3042\u308b\u5927\u80c6\u306a\u7de9\u548c\u3068\u306f\u305d\u306e\u3088\u3046\u306a\u30a4\u30f3\u30d5\u30ec\u6307\u5411\u8def\u7dda\u3067\u3042\u2026",
            "timestamp": "2014-12-13 14:08:41 +0000",
            "tweet_id": "543769479855869952"
        },
        {
            "expanded_urls": "",
            "in_reply_to_status_id": "",
            "in_reply_to_user_id": "",
            "retweeted_status_id": "543757126049345536",
            "retweeted_status_timestamp": "2014-12-13 13:19:36 +0000",
            "retweeted_status_user_id": "350789410",
            "source": "<a href=\"http://twitter.com/#!/download/ipad\" rel=\"nofollow\">Twitter for iPad</a>",
            "text": "RT @hiroshnakagawa3: @unnonouno \u5b9f\u306f\u79c1\u304c\u3068\u3042\u308b\u4f1a\u8b70\u3067\u30a4\u30f3\u30d5\u30ec\uff1d\u5897\u7a0e\u3068\u3044\u3046\u767a\u8a00\u3092\u3057\u305f\u3089\u3001\u9a5a\u3044\u305f\u3001\u521d\u3081\u3066\u805e\u3044\u305f\u307f\u305f\u3044\u306a\u9854\u3092\u3057\u305f\u4eba\u304c\u3044\u307e\u3057\u305f\u3002\u653f\u6cbb\u5bb6\u306b\u305d\u3046\u3044\u3046\u614b\u5ea6\u3092\u8a31\u3059\u306e\u306f\u9078\u6319\u6c11\u306b\u3082\u554f\u984c\u304c\u3042\u308b\u306e\u304b\u3082\u3057\u308c\u306a\u3044\u3002",
            "timestamp": "2014-12-13 14:09:07 +0000",
            "tweet_id": "543769587360096256"
        },
        {
            "expanded_urls": "",
            "in_reply_to_status_id": "",
            "in_reply_to_user_id": "",
            "retweeted_status_id": "543758940387807232",
            "retweeted_status_timestamp": "2014-12-13 13:26:48 +0000",
            "retweeted_status_user_id": "16270589",
            "source": "<a href=\"http://twitter.com/#!/download/ipad\" rel=\"nofollow\">Twitter for iPad</a>",
            "text": "RT @hatopopoko: \u4e0d\u7a4f\u306a\u7a7a\u6c17\u306b\u306a\u3063\u305f\u6642\u306b\u6301\u3063\u3066\u308b\u30d3\u30f3\u673a\u3067\u5272\u305f\u305f\u304d\u3063\u3066\u51f6\u5668\u306b\u3059\u308b\u3084\u3064\u3084\u308a\u305f\u3044",
            "timestamp": "2014-12-13 14:12:23 +0000",
            "tweet_id": "543770410173476864"
        },
        {
            "expanded_urls": "",
            "in_reply_to_status_id": "",
            "in_reply_to_user_id": "",
            "retweeted_status_id": "",
            "retweeted_status_timestamp": "",
            "retweeted_status_user_id": "",
            "source": "<a href=\"http://twitter.com/#!/download/ipad\" rel=\"nofollow\">Twitter for iPad</a>",
            "text": "\u3084\u308a\u305f\u3044",
            "timestamp": "2014-12-13 14:12:33 +0000",
            "tweet_id": "543770454368874496"
        },
        {
            "expanded_urls": "",
            "in_reply_to_status_id": "",
            "in_reply_to_user_id": "",
            "retweeted_status_id": "",
            "retweeted_status_timestamp": "",
            "retweeted_status_user_id": "",
            "source": "<a href=\"http://twitter.com/#!/download/ipad\" rel=\"nofollow\">Twitter for iPad</a>",
            "text": "\u30d5\u30a3\u30af\u30b7\u30e7\u30f3\u3067\u898b\u308b\u30ec\u30a2\u306a\u30b7\u30c1\u30e5\u30a8\u30fc\u30b7\u30e7\u30f3\u4f53\u9a13\u3057\u3066\u307f\u305f\u3044\u6b32\u3063\u3066\u3042\u308b\u3088\u306d",
            "timestamp": "2014-12-13 14:20:24 +0000",
            "tweet_id": "543772427956649984"
        },
        {
            "expanded_urls": "",
            "in_reply_to_status_id": "",
            "in_reply_to_user_id": "",
            "retweeted_status_id": "",
            "retweeted_status_timestamp": "",
            "retweeted_status_user_id": "",
            "source": "<a href=\"http://twitter.com/#!/download/ipad\" rel=\"nofollow\">Twitter for iPad</a>",
            "text": "\u305d\u3046\u3044\u3048\u3070\u3001\u7d4c\u6e08\u5b66\u7684\u306b\u8003\u3048\u308b\u3068\u30ac\u30bd\u30ea\u30f3\u306e\u5024\u6bb5\u304c\u4e0a\u304c\u308b\u3068\u8eca\u306e\u5024\u6bb5\u304c\u4e0b\u304c\u308b\u3068\u3044\u3046\u3053\u3068\u304c\u65e5\u5358\u4f4d\u3067\u8d77\u3053\u3063\u3066\u3044\u3066\u3082\u304a\u304b\u3057\u304f\u306a\u3044\u6c17\u304c\u3059\u308b\u3093\u3060\u3051\u3069\u305d\u3046\u3044\u3046\u3053\u3068\u306f\u8d77\u3053\u3063\u3066\u306a\u3044\u306a\u3002",
            "timestamp": "2014-12-13 14:35:59 +0000",
            "tweet_id": "543776349836419072"
        },
        {
            "expanded_urls": "",
            "in_reply_to_status_id": "",
            "in_reply_to_user_id": "",
            "retweeted_status_id": "",
            "retweeted_status_timestamp": "",
            "retweeted_status_user_id": "",
            "source": "<a href=\"http://twitter.com/#!/download/ipad\" rel=\"nofollow\">Twitter for iPad</a>",
            "text": "\u307c\u304f\u306f\u671f\u65e5\u524d\u6295\u7968\u3092\u3057\u3066\u3044\u305f\u3068\u3044\u3046\u3053\u3068\u3067\u304a\u9858\u3044\u3057\u307e\u3059",
            "timestamp": "2014-12-13 14:42:06 +0000",
            "tweet_id": "543777887837376512"
        },
        {
            "expanded_urls": "",
            "in_reply_to_status_id": "",
            "in_reply_to_user_id": "",
            "retweeted_status_id": "",
            "retweeted_status_timestamp": "",
            "retweeted_status_user_id": "",
            "source": "<a href=\"http://twitter.com/#!/download/ipad\" rel=\"nofollow\">Twitter for iPad</a>",
            "text": "\u30ea\u30a2\u30eb\u3067\u671f\u65e5\u524d\u6295\u7968\u3057\u305f\u3053\u3068\u306b\u3059\u308b\u3068\u624b\u7d9a\u304d\u306e\u8a71\u984c\u306b\u306a\u3063\u305f\u308a\u3057\u305f\u3068\u304d\u306b\u56f0\u308a\u305d\u3046\u3060\u306a\uff08\u305d\u3082\u305d\u3082\u4e16\u9593\u8a71\u3092\u3059\u308b\u76f8\u624b\u304c\u3044\u306a\u3044\u306e\u3067\u56f0\u3089\u306a\u3044\uff09",
            "timestamp": "2014-12-13 14:49:22 +0000",
            "tweet_id": "543779717979983872"
        },
        {
            "expanded_urls": "",
            "in_reply_to_status_id": "",
            "in_reply_to_user_id": "",
            "retweeted_status_id": "",
            "retweeted_status_timestamp": "",
            "retweeted_status_user_id": "",
            "source": "<a href=\"http://twitter.com/#!/download/ipad\" rel=\"nofollow\">Twitter for iPad</a>",
            "text": "\u30ea\u30a2\u30eb\u4e16\u754c\u3068\u3044\u3046\u5b58\u5728\u3001\u30c4\u30a4\u30c3\u30bf\u30fc\u306e\u30cd\u30bf\u306e\u305f\u3081\u306b\u3042\u308b\u3068\u3044\u3046\u6c17\u304c\u65e5\u306b\u65e5\u306b\u5897\u3057\u3066\u3044\u308b",
            "timestamp": "2014-12-13 14:50:08 +0000",
            "tweet_id": "543779909781307393"
        },
        {
            "expanded_urls": "",
            "in_reply_to_status_id": "",
            "in_reply_to_user_id": "",
            "retweeted_status_id": "",
            "retweeted_status_timestamp": "",
            "retweeted_status_user_id": "",
            "source": "<a href=\"http://twitter.com/#!/download/ipad\" rel=\"nofollow\">Twitter for iPad</a>",
            "text": "\u5c06\u6765\u6211\u3005\u304c\u7d14\u7c8b\u306a\u601d\u5ff5\u4f53\u306b\u9032\u5316\u3057\u305f\u3068\u3059\u308b\u3068\u3001\u305d\u306e\u4e16\u754c\u3067\u306f\u8a71\u3059\u30cd\u30bf\u304c\u4f55\u3082\u306a\u3044\u306b\u9055\u3044\u306a\u3044\u3002\u76ee\u3082\u53e3\u3082\u8033\u3082\u306a\u304f\u3001\u7269\u7406\u7684\u306a\u5b9f\u4f53\u306f\u3069\u3053\u306b\u3082\u5b58\u5728\u3057\u306a\u3044\u3002\u305d\u3046\u3044\u3046\u6642\u4ee3\u306b\u5099\u3048\u3066\u3001\u6211\u3005\u306f\u81ea\u5206\u305f\u3061\u304c\u3069\u3046\u3044\u3046\u5f62\u3067\u3042\u3063\u305f\u304b\u3001\u3069\u3046\u3044\u3046\u793e\u4f1a\u3092\u6301\u3063\u3066\u3044\u305f\u304b\u3001\u6027\u5225\u306e\u5b58\u5728\u3001\u7b49\u3005\u3092\u8a71\u306e\u30cd\u30bf\u306e\u305f\u3081\u306b\u899a\u3048\u3066\u304a\u304b\u306d\u3070\u306a\u3089\u306a\u3044",
            "timestamp": "2014-12-13 14:55:09 +0000",
            "tweet_id": "543781171914485760"
        },
        {
            "expanded_urls": "",
            "in_reply_to_status_id": "",
            "in_reply_to_user_id": "",
            "retweeted_status_id": "",
            "retweeted_status_timestamp": "",
            "retweeted_status_user_id": "",
            "source": "<a href=\"http://twitter.com/#!/download/ipad\" rel=\"nofollow\">Twitter for iPad</a>",
            "text": "\u5800\u6c5f\u3068\u304b\u3044\u3046\u6709\u540d\u4eba\u304c\u6709\u540d\u306a\u91e3\u308a\u30cd\u30bf\u306b\u3072\u3063\u304b\u304b\u3063\u305f\u307f\u305f\u3044\u3060\u3051\u3069\u3001\u3069\u3046\u3057\u3066\u3046\u3061\u3089\u3088\u308a\u305a\u3063\u3068\u982d\u304c\u3044\u3044\u306f\u305a\u306e\u4eba\u304c\u3046\u3061\u3089\u307f\u305f\u3044\u306a\u305f\u3060\u306e\u30cd\u30c3\u30c8\u5ec3\u4eba\u306b\u3082\u308f\u304b\u308b\u3088\u3046\u306a\u30cd\u30bf\u306b\u3072\u3063\u304b\u304b\u308b\u306e\uff1f\uff08\u7b54\u3048\uff1a\u30cd\u30c3\u30c8\u5ec3\u4eba\u3058\u3083\u306a\u3044\u304b\u3089\uff09",
            "timestamp": "2014-12-13 15:09:31 +0000",
            "tweet_id": "543784787794620418"
        },
        {
            "expanded_urls": "",
            "in_reply_to_status_id": "",
            "in_reply_to_user_id": "",
            "retweeted_status_id": "543783177072803840",
            "retweeted_status_timestamp": "2014-12-13 15:03:07 +0000",
            "retweeted_status_user_id": "42027820",
            "source": "<a href=\"http://twitter.com/#!/download/ipad\" rel=\"nofollow\">Twitter for iPad</a>",
            "text": "RT @echizen_tm: \u30ad\u30e3\u30d7\u30c6\u30f3\u30fb\u30d5\u30e5\u30fc\u30c1\u30e3\u30fc\u3068\u3044\u3046\u4f5c\u54c1\u3002\u30b5\u30a4\u30e2\u30f3\u535a\u58eb\u304c\u3046\u307e\u3044\u3053\u3068\u4eba\u3068\u96e2\u5225\u3057\u3066\u8089\u4f53\u3092\u6301\u305f\u306a\u3044\u6700\u9ad8\u306e\u72b6\u614b\u306b\u306a\u3063\u305f\u306e\u306b\u3001\u793e\u4f1a\u304c\u8089\u4f53\u3092\u6301\u3064\u524d\u63d0\u3067\u69cb\u6210\u3055\u308c\u3066\u3044\u305f\u306e\u3067\u3001\u751f\u304d\u308b\u305f\u3081\u306b\u30b7\u30ea\u30fc\u30ba\u304c\u9032\u3080\u306b\u9023\u308c\u3066\u73fe\u5b9f\u4e16\u754c\u306b\u5e72\u6e09\u3059\u308b\u30a4\u30f3\u30bf\u30d5\u30a7\u30fc\u30b9\u3092\u88c5\u5099\u3059\u308b\u7fbd\u76ee\u306b\u306a\u308b\u3001\u3068\u3044\u3046\u2026",
            "timestamp": "2014-12-13 15:11:01 +0000",
            "tweet_id": "543785167249096704"
        },
        {
            "expanded_urls": "",
            "in_reply_to_status_id": "",
            "in_reply_to_user_id": "",
            "retweeted_status_id": "",
            "retweeted_status_timestamp": "",
            "retweeted_status_user_id": "",
            "source": "<a href=\"http://twitter.com/#!/download/ipad\" rel=\"nofollow\">Twitter for iPad</a>",
            "text": "\u8eca\u3092\u904b\u8ee2\u3059\u308b\u305f\u3073\u306b\uff08\u30ac\u30bd\u30ea\u30f3\u4ee3\u60c5\u5831\u3092\u81ea\u52d5\u53d7\u4fe1\u3057\u3066\uff09\u4eca\u56de\u304b\u304b\u3063\u305f\u30ac\u30bd\u30ea\u30f3\u4ee3\u3092\u8868\u793a\u3059\u308b\u4ed5\u7d44\u307f\u3092\u3059\u3079\u3066\u306e\u8eca\u306b\u642d\u8f09\u3055\u305b\u305f\u3089\u52b9\u7387\u7684\u306bGDP\u843d\u3068\u305b\u305d\u3046",
            "timestamp": "2014-12-13 15:15:37 +0000",
            "tweet_id": "543786324730191872"
        },
        {
            "expanded_urls": "",
            "in_reply_to_status_id": "",
            "in_reply_to_user_id": "",
            "retweeted_status_id": "",
            "retweeted_status_timestamp": "",
            "retweeted_status_user_id": "",
            "source": "<a href=\"http://itunes.apple.com/us/app/twitter/id409789998?mt=12\" rel=\"nofollow\">Twitter for Mac</a>",
            "text": "\u306a\u305c\u8eca\u306e\u5024\u6bb5\u304c\u30ac\u30bd\u30ea\u30f3\u4ee3\u3068\u53cd\u5bfe\u306b\u3059\u3050\u52d5\u304b\u306a\u3044\u306e\u304b\u554f\u984c\u304c\u4f9d\u7136\u6c17\u306b\u306a\u3063\u3066\u3044\u308b\u3002\u4f55\u3068\u304b\u3064\u3051\u3044\u308b\u9699\u306f\u306a\u3044\u3060\u308d\u3046\u304b\u2026\u3002",
            "timestamp": "2014-12-13 15:30:34 +0000",
            "tweet_id": "543790088514056192"
        },
        {
            "expanded_urls": "",
            "in_reply_to_status_id": "",
            "in_reply_to_user_id": "",
            "retweeted_status_id": "",
            "retweeted_status_timestamp": "",
            "retweeted_status_user_id": "",
            "source": "<a href=\"http://itunes.apple.com/us/app/twitter/id409789998?mt=12\" rel=\"nofollow\">Twitter for Mac</a>",
            "text": "\u305d\u3046\u3044\u3048\u3070\u3001\u307c\u304f\u306f\u5165\u308b\u304a\u91d1\u304b\u3089\u4f7f\u3046\u304a\u91d1\u3092\u5f15\u3044\u3066\u8caf\u91d1\u3059\u308b\u611f\u3058\u306a\u3093\u3060\u3051\u3069\u3001\u59bb\u306f\u5165\u308b\u304a\u91d1\u304b\u3089\u8caf\u91d1\u3059\u308b\u304a\u91d1\u3092\u5f15\u3044\u3066\u4f7f\u3046\u611f\u3058\u3060\u3002",
            "timestamp": "2014-12-13 15:37:33 +0000",
            "tweet_id": "543791844950159360"
        },
        {
            "expanded_urls": "",
            "in_reply_to_status_id": "",
            "in_reply_to_user_id": "",
            "retweeted_status_id": "",
            "retweeted_status_timestamp": "",
            "retweeted_status_user_id": "",
            "source": "<a href=\"http://itunes.apple.com/us/app/twitter/id409789998?mt=12\" rel=\"nofollow\">Twitter for Mac</a>",
            "text": "\u4eca\u306b\u306a\u3063\u3066\u3084\u3063\u3068\u300c\u30ed\u30b6\u30ea\u30aa\u300d\u3068\u3044\u3046\u3082\u306e\u306e\u5b9f\u4f53\u304c\u3069\u3046\u3044\u3046\u3082\u306e\u304b\u3092\u77e5\u3063\u305f\uff08\u643a\u5e2f\u53ef\u80fd\u306a\u56fa\u5f62\u7269\u3067\u3042\u308b\u3068\u3044\u3046\u3053\u3068\u4ee5\u4e0a\u306e\u60c5\u5831\u3092\u6301\u3063\u3066\u3044\u306a\u304b\u3063\u305f\uff09",
            "timestamp": "2014-12-13 15:42:12 +0000",
            "tweet_id": "543793016444444672"
        },
        {
            "expanded_urls": "",
            "in_reply_to_status_id": "",
            "in_reply_to_user_id": "",
            "retweeted_status_id": "",
            "retweeted_status_timestamp": "",
            "retweeted_status_user_id": "",
            "source": "<a href=\"http://itunes.apple.com/us/app/twitter/id409789998?mt=12\" rel=\"nofollow\">Twitter for Mac</a>",
            "text": "\u305d\u3046\u3044\u3048\u3070\u4eba\u9593\u306f\u300c\u601d\u8003\u505c\u6b62\u300d\u3068\u3044\u3046\u3053\u3068\u304c\u3067\u304d\u308b\u3051\u308c\u3069\u3001\u3042\u308c\u306f\u52d5\u7269\u7684\u306a\u30d5\u30a9\u30fc\u30eb\u30d0\u30c3\u30af\u30b7\u30b9\u30c6\u30e0\u304c\u3042\u308b\u304b\u3089\u3067\u304d\u308b\u3053\u3068\u306a\u3093\u3060\u3088\u306a\u3041\uff08\u307c\u304f\u306f\u601d\u8003\u505c\u6b62\u3059\u308b\u3068\u52d5\u4f5c\u505c\u6b62\u3059\u308b\uff09\uff08\u3059\u308b\u3053\u3068\u3082\u3042\u308b\uff09",
            "timestamp": "2014-12-13 15:54:45 +0000",
            "tweet_id": "543796174818246657"
        },
        {
            "expanded_urls": "",
            "in_reply_to_status_id": "",
            "in_reply_to_user_id": "",
            "retweeted_status_id": "",
            "retweeted_status_timestamp": "",
            "retweeted_status_user_id": "",
            "source": "<a href=\"http://itunes.apple.com/us/app/twitter/id409789998?mt=12\" rel=\"nofollow\">Twitter for Mac</a>",
            "text": "\u4f8b\u3048\u3070\u300c\u30e9\u30f3\u30c0\u30e0\u3067\u6295\u7968\u3059\u308b\u4eba\u306e\u6295\u7968\u7d50\u679c\u306f\u305f\u3060\u306e\u30ce\u30a4\u30ba\u3060\u304b\u3089\u6295\u7968\u306b\u884c\u304b\u306a\u3044\u306e\u3068\u4e0d\u9053\u5fb3\u3060\u300d\u3068\u3044\u3046\u4e3b\u5f35\u3092\u3059\u308b\u3068\u3059\u308b\u3002\u3053\u308c\u306f\u8868\u9762\u7684\u306b\u306f\u7406\u5c48\u304c\u901a\u3063\u3066\u3044\u308b\u3002\u3057\u304b\u3057\u3001\u5b9f\u969b\u306f\u6295\u7968\u306b\u884c\u304b\u306a\u3044\u306e\u3060\u3051\u304c\u4e0d\u9053\u5fb3\u3060\u3002\u305d\u306e\u7406\u7531\u306f\u5fe0\u8aa0\u5fc3\u304c\u8db3\u308a\u306a\u3044\u304b\u3089\u3060\u3002\u3060\u304c\u4eba\u9593\u306f\u305d\u308c\u3092\u8868\u5411\u304d\u8a8d\u3081\u3089\u308c\u306a\u3044\u3002\u305d\u3057\u3066\u601d\u8003\u505c\u6b62\u3059\u308b\u3002",
            "timestamp": "2014-12-13 15:59:09 +0000",
            "tweet_id": "543797282185822209"
        },
        {
            "expanded_urls": "",
            "in_reply_to_status_id": "",
            "in_reply_to_user_id": "",
            "retweeted_status_id": "",
            "retweeted_status_timestamp": "",
            "retweeted_status_user_id": "",
            "source": "<a href=\"http://itunes.apple.com/us/app/twitter/id409789998?mt=12\" rel=\"nofollow\">Twitter for Mac</a>",
            "text": "\u306a\u3044\u306e\u3068\u2192\u306a\u3044\u306e\u3068\u540c\u3058\u3050\u3089\u3044\uff08\u6587\u5b57\u6570\u8abf\u6574\u306b\u5931\u6557\u3057\u305f\uff09",
            "timestamp": "2014-12-13 15:59:47 +0000",
            "tweet_id": "543797439421894656"
        },
        {
            "expanded_urls": "",
            "in_reply_to_status_id": "",
            "in_reply_to_user_id": "",
            "retweeted_status_id": "",
            "retweeted_status_timestamp": "",
            "retweeted_status_user_id": "",
            "source": "<a href=\"http://itunes.apple.com/us/app/twitter/id409789998?mt=12\" rel=\"nofollow\">Twitter for Mac</a>",
            "text": "\u305d\u3057\u3066\u3001\u4eba\u9593\u306f\u90fd\u5408\u306e\u60aa\u3044\u3082\u306e\u304c\u76ee\u306b\u5165\u3089\u306a\u3044\u6a5f\u69cb\u304c\u3042\u308b\u306e\u3067\u3001\u3053\u3046\u3044\u3046\u3053\u3068\u3092\u66f8\u3044\u3066\u3082\u30a2\u30b9\u30da\uff08\u7591\u3044\uff09\u306e\u4eba\u306b\u3057\u304b\u5c4a\u304b\u306a\u3044\u306e\u3060\u3002",
            "timestamp": "2014-12-13 16:00:43 +0000",
            "tweet_id": "543797673204015104"
        },
        {
            "expanded_urls": "",
            "in_reply_to_status_id": "",
            "in_reply_to_user_id": "",
            "retweeted_status_id": "",
            "retweeted_status_timestamp": "",
            "retweeted_status_user_id": "",
            "source": "<a href=\"http://itunes.apple.com/us/app/twitter/id409789998?mt=12\" rel=\"nofollow\">Twitter for Mac</a>",
            "text": "\u3053\u306e\u601d\u8003\u505c\u6b62\u3068\u3044\u3046\u6a5f\u69cb\u306f\u4eba\u9593\u306e\u6016\u3044\u3068\u3053\u308d\u3067\u306f\u3042\u308b\u306e\u3060\u304c\u3001\u4eba\u9593\u304b\u3089\u30a2\u30b9\u30da\u3092\u898b\u308b\u3068\u307e\u305f\u5225\u306e\u6016\u3044\u3068\u3053\u308d\uff08\u306e\u3088\u3046\u306b\u898b\u3048\u308b\u6a5f\u69cb\uff09\u304c\u3042\u308b\u306e\u304b\u3082\u3057\u308c\u306a\u3044\u3001\u3063\u3066\u601d\u3063\u305f\u3089\u305d\u308c\u306f\u307e\u3055\u306b\u5171\u611f\u80fd\u529b\u306e\u6b20\u5982\u3068\u3044\u3046\u3068\u3053\u308d\u3060\u3063\u305f\u3002\uff08\u3057\u304b\u3057\u3053\u308c\u306f\u30a2\u30b9\u30da\u5074\u306b\u3042\u308b\u6a5f\u69cb\u3067\u306f\u306a\u304f\u4eba\u9593\u5074\u306b\u3042\u308b\u6a5f\u69cb\u3060\uff09",
            "timestamp": "2014-12-13 16:02:58 +0000",
            "tweet_id": "543798242274586624"
        },
        {
            "expanded_urls": "",
            "in_reply_to_status_id": "",
            "in_reply_to_user_id": "",
            "retweeted_status_id": "",
            "retweeted_status_timestamp": "",
            "retweeted_status_user_id": "",
            "source": "<a href=\"http://itunes.apple.com/us/app/twitter/id409789998?mt=12\" rel=\"nofollow\">Twitter for Mac</a>",
            "text": "\u4f55\u304b\u6700\u8fd1\u307e\u305f\u4eba\u9593\u306b\u3064\u3044\u3066\u8003\u3048\u308b\u3053\u3068\u304c\u591a\u304f\u306a\u3063\u3066\u308b\u306a\u3001\u3069\u3046\u3057\u3066\u304b\u306a\u3001\u3068\u601d\u3063\u305f\u3089\u3054\u304f\u5f53\u305f\u308a\u524d\u306b\u9078\u6319\u306e\u305b\u3044\u3060\u3063\u305f",
            "timestamp": "2014-12-13 16:05:43 +0000",
            "tweet_id": "543798933416185856"
        },
        {
            "expanded_urls": "http://takeda25.hatenablog.com/entry/2014/12/13/000000",
            "in_reply_to_status_id": "",
            "in_reply_to_user_id": "",
            "retweeted_status_id": "",
            "retweeted_status_timestamp": "",
            "retweeted_status_user_id": "",
            "source": "<a href=\"http://www.hatena.ne.jp/guide/twitter\" rel=\"nofollow\">Hatena</a>",
            "text": "\u306f\u3066\u306a\u30d6\u30ed\u30b0\u306b\u6295\u7a3f\u3057\u307e\u3057\u305f\n12/13 - takeda25\u306e\u65e5\u8a18\nhttp://t.co/QvhnSsoEMC",
            "timestamp": "2014-12-13 17:07:01 +0000",
            "tweet_id": "543814360632541185"
        },
        {
            "expanded_urls": "",
            "in_reply_to_status_id": "",
            "in_reply_to_user_id": "",
            "retweeted_status_id": "543816214254850048",
            "retweeted_status_timestamp": "2014-12-13 17:14:23 +0000",
            "retweeted_status_user_id": "166888744",
            "source": "<a href=\"http://itunes.apple.com/us/app/twitter/id409789998?mt=12\" rel=\"nofollow\">Twitter for Mac</a>",
            "text": "RT @ottwo: \u3053\u308c\u306f\u5197\u8ac7\u3058\u3083\u306a\u3044\u3093\u3060\u3051\u3069\u3001\u300c\u4eba\u306f\u3044\u3064\u304b\u6b7b\u306c\u300d\u3063\u3066\u5b50\u4f9b\u306e\u9803\u306f\u975e\u5e38\u306b\u6df1\u523b\u306a\u30cd\u30bf\u30d0\u30ec\u3060\u3063\u305f\u3088",
            "timestamp": "2014-12-13 17:17:13 +0000",
            "tweet_id": "543816927286542336"
        },
        {
            "expanded_urls": "https://twitter.com/ottwo/status/543816214254850048",
            "in_reply_to_status_id": "",
            "in_reply_to_user_id": "",
            "retweeted_status_id": "",
            "retweeted_status_timestamp": "",
            "retweeted_status_user_id": "",
            "source": "<a href=\"http://itunes.apple.com/us/app/twitter/id409789998?mt=12\" rel=\"nofollow\">Twitter for Mac</a>",
            "text": "\u3053\u306e\u611f\u899a\u306a\u3044\u306a\u30fc https://t.co/qVIr6yuzRX",
            "timestamp": "2014-12-13 17:17:30 +0000",
            "tweet_id": "543816999478902784"
        },
        {
            "expanded_urls": "",
            "in_reply_to_status_id": "",
            "in_reply_to_user_id": "",
            "retweeted_status_id": "",
            "retweeted_status_timestamp": "",
            "retweeted_status_user_id": "",
            "source": "<a href=\"http://itunes.apple.com/us/app/twitter/id409789998?mt=12\" rel=\"nofollow\">Twitter for Mac</a>",
            "text": "\u305d\u3082\u305d\u3082\u3042\u3093\u307e\u308a\u9577\u671f\u7684\u306b\u3082\u306e\u3092\u8003\u3048\u3089\u308c\u306a\u3044\u3068\u3053\u308d\u304c\u3042\u308b",
            "timestamp": "2014-12-13 17:18:20 +0000",
            "tweet_id": "543817207470247936"
        },
        {
            "expanded_urls": "",
            "in_reply_to_status_id": "",
            "in_reply_to_user_id": "",
            "retweeted_status_id": "",
            "retweeted_status_timestamp": "",
            "retweeted_status_user_id": "",
            "source": "<a href=\"http://itunes.apple.com/us/app/twitter/id409789998?mt=12\" rel=\"nofollow\">Twitter for Mac</a>",
            "text": "\u3044\u3064\u304b\u6b7b\u306c\u3068\u3044\u3046\u304b\u3001\u660e\u65e5\u751f\u304d\u3066\u3044\u308b\u304b\u3069\u3046\u304b\u3082\u308f\u304b\u3089\u306a\u3044\uff08\u3068\u3044\u3046\u306e\u306f\u307f\u3093\u306a\u6982\u5ff5\u7684\u306b\u306f\u308f\u304b\u3063\u3066\u3044\u308b\u3068\u306f\u601d\u3046\u3051\u308c\u3069\u3001\u307c\u304f\u306f\u305d\u3046\u3044\u3046\u306e\u304c\u611f\u899a\u7684\u306b\u3042\u308b\uff09",
            "timestamp": "2014-12-13 17:19:14 +0000",
            "tweet_id": "543817432393986049"
        },
        {
            "expanded_urls": "",
            "in_reply_to_status_id": "",
            "in_reply_to_user_id": "",
            "retweeted_status_id": "",
            "retweeted_status_timestamp": "",
            "retweeted_status_user_id": "",
            "source": "<a href=\"http://itunes.apple.com/us/app/twitter/id409789998?mt=12\" rel=\"nofollow\">Twitter for Mac</a>",
            "text": "\u59bb\u304b\u3089\u3061\u3087\u3063\u3068\u9023\u7d61\u304c\u306a\u304b\u3063\u305f\u308a\u3059\u308b\u3068\u3059\u3050\u306b\u6b7b\u3068\u3044\u3046\u9078\u629e\u80a2\u304c\u982d\u306b\u6d6e\u304b\u3076\uff08\u3068\u3044\u3063\u3066\u3082\u305d\u308c\u306b\u3088\u3063\u3066\u3046\u308d\u305f\u3048\u308b\u3068\u3044\u3046\u3053\u3068\u3067\u306f\u306a\u3044\uff09",
            "timestamp": "2014-12-13 17:20:30 +0000",
            "tweet_id": "543817752012546048"
        },
        {
            "expanded_urls": "",
            "in_reply_to_status_id": "",
            "in_reply_to_user_id": "",
            "retweeted_status_id": "",
            "retweeted_status_timestamp": "",
            "retweeted_status_user_id": "",
            "source": "<a href=\"http://itunes.apple.com/us/app/twitter/id409789998?mt=12\" rel=\"nofollow\">Twitter for Mac</a>",
            "text": "\u9078\u629e\u80a2\u3058\u3083\u306a\u3044\u3001\u53ef\u80fd\u6027\u3060\uff08\u5927\u304d\u306a\u9593\u9055\u3044\uff09",
            "timestamp": "2014-12-13 17:21:05 +0000",
            "tweet_id": "543817898037223424"
        },
        {
            "expanded_urls": "",
            "in_reply_to_status_id": "",
            "in_reply_to_user_id": "",
            "retweeted_status_id": "",
            "retweeted_status_timestamp": "",
            "retweeted_status_user_id": "",
            "source": "<a href=\"http://itunes.apple.com/us/app/twitter/id409789998?mt=12\" rel=\"nofollow\">Twitter for Mac</a>",
            "text": "\u4f55\u304b\u69cb\u9020\u7684\u306b\u6b20\u9665\u304c\u3042\u308b\u6c17\u304c\u3059\u308b",
            "timestamp": "2014-12-13 17:21:34 +0000",
            "tweet_id": "543818021781770240"
        },
        {
            "expanded_urls": "",
            "in_reply_to_status_id": "",
            "in_reply_to_user_id": "",
            "retweeted_status_id": "",
            "retweeted_status_timestamp": "",
            "retweeted_status_user_id": "",
            "source": "<a href=\"http://itunes.apple.com/us/app/twitter/id409789998?mt=12\" rel=\"nofollow\">Twitter for Mac</a>",
            "text": "\u307c\u304f\u306f\u751f\u80b2\u74b0\u5883\u306b\u3088\u3063\u3066\u4e0d\u5e78\u306b\u306a\u3063\u305f\u3068\u3053\u308d\u304c\u5927\u304d\u3044\u3068\u601d\u3063\u3066\u3044\u305f\u3051\u308c\u3069\u3001\u81ea\u5206\u306e\u751f\u304d\u5199\u3057\u306e\u3088\u3046\u306a\u5b50\u4f9b\u3092\u898b\u3066\u3044\u308b\u3068\u3069\u3046\u30828\u5272\u3050\u3089\u3044\u306f\u907a\u4f1d\u3067\u4e0d\u5e78\u306b\u306a\u3063\u3066\u3044\u305f\u3088\u3046\u3067\u30a2\u30ec\u3067\u3042\u308b\uff08\u3057\u304b\u30572\u5272\u306f\u74b0\u5883\u3067\u4e0d\u5e78\u306b\u306a\u3063\u305f\u3068\u601d\u3046\u3051\u3069\uff09",
            "timestamp": "2014-12-13 17:24:27 +0000",
            "tweet_id": "543818745496363009"
        },
        {
            "expanded_urls": "",
            "in_reply_to_status_id": "",
            "in_reply_to_user_id": "",
            "retweeted_status_id": "",
            "retweeted_status_timestamp": "",
            "retweeted_status_user_id": "",
            "source": "<a href=\"http://twitter.com/#!/download/ipad\" rel=\"nofollow\">Twitter for iPad</a>",
            "text": "\u30a2\u30b9\u30da\u3068\u3064\u3089\u3044\u4eba\u9593\u3001\u307b\u3068\u3093\u3069\u540c\u3058\u3088\u3046\u306b\u898b\u3048\u308b\u3057\u5b9f\u969b\u8fd1\u3044\u3093\u3060\u3051\u3069\u3001\u5185\u90e8\u6a5f\u69cb\u306f\u76f8\u5f53\u9055\u3046\u306e\u3067\u671f\u5f85\u3057\u3059\u304e\u3066\u3082\u3088\u304f\u306a\u3044\u3057\u3001\u96e3\u3057\u3044\u3068\u3053\u308d",
            "timestamp": "2014-12-13 17:43:32 +0000",
            "tweet_id": "543823547949273089"
        }
    ]
}